Workbook

Sheet Inputs
A1: Perspective | B1: Description | C1: Question | D1: User Response | E1: Numeric Score | F1: Individual Capability Strategy | G1: T-Shirt Sizing
A2: Compute & Operating System Fit: | B2: (Operating System Support) | C2: A) Legacy Proprietary: Running on an obsolete, proprietary Unix variant (e.g., AIX, Solaris, HP-UX) with zero native translation to public cloud instances. B) Outdated Commercial: Running on an enterprise OS (e.g., Windows Server 2008/2012, RHEL 5/6) that is end-of-life and requires expensive custom support or migration hurdles. C) Standard Modern: Running on a current, mainstream OS version (e.g., Windows Server 2019/2022, RHEL 8/9, Ubuntu 20/22) fully supported by cloud base images. D) OS-Agnostic / Containerized: Entirely decoupled from the host OS; package runs natively inside lightweight, platform-independent containers (e.g., Docker/OCI images). | D2: D | E2: {=_xlfn.IFS(D2="A", 1, D2="B", 2, D2="C", 3, D2="D", 4, TRUE, 0)} -> 4 | F2: {=_xlfn.IFS( E2=1, _xlfn.IFS( A2="Security, Identity & Compliance", "RETAIN (Critical Legal/Sovereignty Roadblock)", A2="Compute & Operating System Fit", "RETIRE / SCRAP (Obsolete Hardware/OS Profile)", TRUE, "RETAIN (Fatal System/Dependency Blocker)" ), E2=2, _xlfn.IFS( A2="Software Lifecycle & Maintainability", "REFACTOR (Deep Code Rewrite Required)", A2="Compute & Operating System Fit", "RELOCATE (Lift-to-Cloud VMware/Hypervisor Cluster)", TRUE, "REFACTOR / RE-ARCHITECT (High Migration Debt)" ), E2=3, _xlfn.IFS( A2="Data & Storage Tier Compatibility", "REPLATFORM (Swap to Managed Cloud DB / Object Store)", A2="Networking, Integration & Performance", "REPLATFORM (Swap to Cloud ALB / CloudFront CDN)", TRUE, "REPLATFORM / LIFT-AND-SHAPE" ), E2=4, _xlfn.IFS( A2="Software Lifecycle & Maintainability", "REPURCHASE (Replace with Turnkey SaaS Product)", TRUE, "REHOST (LIFT & SHIFT) (Direct VM Migration Ready)" ), TRUE, "" )} -> REHOST (LIFT & SHIFT) (Direct VM Migration Ready) | G2: Small
A3: Compute & Operating System Fit: | B3: (OS Version Currency) | C3: A) Severely Custom / Hardened: The OS has been heavily modified with custom kernel patches or custom configurations that make it impossible to upgrade without breaking the application code. B) Patch Lagging: Running a standard OS but lagging multiple years behind security patches, requiring a dedicated upgrading phase before migration. C) N-1 Current: Up to date within one major release cycle; can be clean-imaged directly to the cloud with minimal verification testing. D) Auto-Immutable: Deployed using automated, immutable base images that are continuously destroyed, rebuilt, and patched via automated pipelines. | D3: D | E3: {=_xlfn.IFS(D3="A", 1, D3="B", 2, D3="C", 3, D3="D", 4, TRUE, 0)} -> 4 | F3: {=_xlfn.IFS( E3=1, _xlfn.IFS( A3="Security, Identity & Compliance", "RETAIN (Critical Legal/Sovereignty Roadblock)", A3="Compute & Operating System Fit", "RETIRE / SCRAP (Obsolete Hardware/OS Profile)", TRUE, "RETAIN (Fatal System/Dependency Blocker)" ), E3=2, _xlfn.IFS( A3="Software Lifecycle & Maintainability", "REFACTOR (Deep Code Rewrite Required)", A3="Compute & Operating System Fit", "RELOCATE (Lift-to-Cloud VMware/Hypervisor Cluster)", TRUE, "REFACTOR / RE-ARCHITECT (High Migration Debt)" ), E3=3, _xlfn.IFS( A3="Data & Storage Tier Compatibility", "REPLATFORM (Swap to Managed Cloud DB / Object Store)", A3="Networking, Integration & Performance", "REPLATFORM (Swap to Cloud ALB / CloudFront CDN)", TRUE, "REPLATFORM / LIFT-AND-SHAPE" ), E3=4, _xlfn.IFS( A3="Software Lifecycle & Maintainability", "REPURCHASE (Replace with Turnkey SaaS Product)", TRUE, "REHOST (LIFT & SHIFT) (Direct VM Migration Ready)" ), TRUE, "" )} -> REHOST (LIFT & SHIFT) (Direct VM Migration Ready) | G3: Medium
A4: Compute & Operating System Fit: | B4: (Kernel & Driver Dependencies) | C4: A) Bare-Metal Hardware Ties: Relies on dedicated, physical on-premises hardware components (e.g., physical USB license dongles, custom PCI-e acceleration cards). B) Custom Kernel Extensions: Requires specialized, proprietary OS kernel modules or hypervisor-specific integration tools to execute basic tasks. C) Standard User-Space: Operates entirely within standard user-space environments; requires no custom drivers, kernel tweaks, or specialized hardware permissions. D) Fully Virtualized Core: Built specifically to leverage abstracted virtual resources, adapting fluidly across differing cloud instance hypervisors. | D4: D | E4: {=_xlfn.IFS(D4="A", 1, D4="B", 2, D4="C", 3, D4="D", 4, TRUE, 0)} -> 4 | F4: {=_xlfn.IFS( E4=1, _xlfn.IFS( A4="Security, Identity & Compliance", "RETAIN (Critical Legal/Sovereignty Roadblock)", A4="Compute & Operating System Fit", "RETIRE / SCRAP (Obsolete Hardware/OS Profile)", TRUE, "RETAIN (Fatal System/Dependency Blocker)" ), E4=2, _xlfn.IFS( A4="Software Lifecycle & Maintainability", "REFACTOR (Deep Code Rewrite Required)", A4="Compute & Operating System Fit", "RELOCATE (Lift-to-Cloud VMware/Hypervisor Cluster)", TRUE, "REFACTOR / RE-ARCHITECT (High Migration Debt)" ), E4=3, _xlfn.IFS( A4="Data & Storage Tier Compatibility", "REPLATFORM (Swap to Managed Cloud DB / Object Store)", A4="Networking, Integration & Performance", "REPLATFORM (Swap to Cloud ALB / CloudFront CDN)", TRUE, "REPLATFORM / LIFT-AND-SHAPE" ), E4=4, _xlfn.IFS( A4="Software Lifecycle & Maintainability", "REPURCHASE (Replace with Turnkey SaaS Product)", TRUE, "REHOST (LIFT & SHIFT) (Direct VM Migration Ready)" ), TRUE, "" )} -> REHOST (LIFT & SHIFT) (Direct VM Migration Ready) | G4: Small
A5: Compute & Operating System Fit: | B5: (Hardware Architecture) | C5: A) Monolithic Mainframe: Built for legacy mainframe or specialized mid-range architectures (e.g., IBM AS/400, IBM z/OS) with no x86/ARM equivalent. B) High-Spec Large Scale: Requires massive, specialized single-node on-premises configurations (e.g., 128+ cores, 2TB+ RAM) that are prohibitively expensive or restricted in the cloud. C) Standard x86: Runs on standard, commodity x86 64-bit multi-core processors easily matched by 99% of cloud instance families. D) ARM / Micro-Architecture Efficient: Native support for modern, highly efficient ARM-based cloud architectures (e.g., AWS Graviton or Azure Ampere), drastically lowering compute costs | D5: D | E5: {=_xlfn.IFS(D5="A", 1, D5="B", 2, D5="C", 3, D5="D", 4, TRUE, 0)} -> 4 | F5: {=_xlfn.IFS( E5=1, _xlfn.IFS( A5="Security, Identity & Compliance", "RETAIN (Critical Legal/Sovereignty Roadblock)", A5="Compute & Operating System Fit", "RETIRE / SCRAP (Obsolete Hardware/OS Profile)", TRUE, "RETAIN (Fatal System/Dependency Blocker)" ), E5=2, _xlfn.IFS( A5="Software Lifecycle & Maintainability", "REFACTOR (Deep Code Rewrite Required)", A5="Compute & Operating System Fit", "RELOCATE (Lift-to-Cloud VMware/Hypervisor Cluster)", TRUE, "REFACTOR / RE-ARCHITECT (High Migration Debt)" ), E5=3, _xlfn.IFS( A5="Data & Storage Tier Compatibility", "REPLATFORM (Swap to Managed Cloud DB / Object Store)", A5="Networking, Integration & Performance", "REPLATFORM (Swap to Cloud ALB / CloudFront CDN)", TRUE, "REPLATFORM / LIFT-AND-SHAPE" ), E5=4, _xlfn.IFS( A5="Software Lifecycle & Maintainability", "REPURCHASE (Replace with Turnkey SaaS Product)", TRUE, "REHOST (LIFT & SHIFT) (Direct VM Migration Ready)" ), TRUE, "" )} -> REHOST (LIFT & SHIFT) (Direct VM Migration Ready) | G5: Large
A6: Compute & Operating System Fit: | B6: (Compute Elasticity) | C6: A) Monolithic Continuous: Must run 24/7 at fixed utilization; crashing or scaling down takes hours of manual initialization and synchronization routines. B) Stateful Inelastic: The workload experiences heavy traffic spikes, but cannot scale dynamically because user session states are bound rigidly to server memory. C) Auto-Scaling Compatible: Completely decoupled from state; can gracefully spin up or terminate instances in minutes via standard metric-driven autoscaling groups. D) Event-Driven Serverless: Operates on ephemeral, event-driven compute functions (e.g., AWS Lambda, Azure Functions); scales from zero to thousands of concurrent executions instantly. | D6: D | E6: {=_xlfn.IFS(D6="A", 1, D6="B", 2, D6="C", 3, D6="D", 4, TRUE, 0)} -> 4 | F6: {=_xlfn.IFS( E6=1, _xlfn.IFS( A6="Security, Identity & Compliance", "RETAIN (Critical Legal/Sovereignty Roadblock)", A6="Compute & Operating System Fit", "RETIRE / SCRAP (Obsolete Hardware/OS Profile)", TRUE, "RETAIN (Fatal System/Dependency Blocker)" ), E6=2, _xlfn.IFS( A6="Software Lifecycle & Maintainability", "REFACTOR (Deep Code Rewrite Required)", A6="Compute & Operating System Fit", "RELOCATE (Lift-to-Cloud VMware/Hypervisor Cluster)", TRUE, "REFACTOR / RE-ARCHITECT (High Migration Debt)" ), E6=3, _xlfn.IFS( A6="Data & Storage Tier Compatibility", "REPLATFORM (Swap to Managed Cloud DB / Object Store)", A6="Networking, Integration & Performance", "REPLATFORM (Swap to Cloud ALB / CloudFront CDN)", TRUE, "REPLATFORM / LIFT-AND-SHAPE" ), E6=4, _xlfn.IFS( A6="Software Lifecycle & Maintainability", "REPURCHASE (Replace with Turnkey SaaS Product)", TRUE, "REHOST (LIFT & SHIFT) (Direct VM Migration Ready)" ), TRUE, "" )} -> REHOST (LIFT & SHIFT) (Direct VM Migration Ready) | G6: Medium
A7: Compute & Operating System Fit: | B7: (Virtualization Compatibility) | C7: A) Bare-Metal Direct: Hardwired directly to physical hardware layers; cannot run inside a hypervisor or standard virtual machine wrapper without catastrophic performance loss. B) Nested Hypervisor Bound: Locked into complex VMware-specific clustering features (e.g., vMotion, Raw Device Mapping) that limit migration options. C) Standard VM Ready: Runs cleanly inside any standard virtualization layer; can be exported directly via standard VM migration tools (e.g., OVF templates). D) Cloud Native Container: Built using micro-footprint container models, completely abstracted away from virtual machine infrastructure dependencies | D7: D | E7: {=_xlfn.IFS(D7="A", 1, D7="B", 2, D7="C", 3, D7="D", 4, TRUE, 0)} -> 4 | F7: {=_xlfn.IFS( E7=1, _xlfn.IFS( A7="Security, Identity & Compliance", "RETAIN (Critical Legal/Sovereignty Roadblock)", A7="Compute & Operating System Fit", "RETIRE / SCRAP (Obsolete Hardware/OS Profile)", TRUE, "RETAIN (Fatal System/Dependency Blocker)" ), E7=2, _xlfn.IFS( A7="Software Lifecycle & Maintainability", "REFACTOR (Deep Code Rewrite Required)", A7="Compute & Operating System Fit", "RELOCATE (Lift-to-Cloud VMware/Hypervisor Cluster)", TRUE, "REFACTOR / RE-ARCHITECT (High Migration Debt)" ), E7=3, _xlfn.IFS( A7="Data & Storage Tier Compatibility", "REPLATFORM (Swap to Managed Cloud DB / Object Store)", A7="Networking, Integration & Performance", "REPLATFORM (Swap to Cloud ALB / CloudFront CDN)", TRUE, "REPLATFORM / LIFT-AND-SHAPE" ), E7=4, _xlfn.IFS( A7="Software Lifecycle & Maintainability", "REPURCHASE (Replace with Turnkey SaaS Product)", TRUE, "REHOST (LIFT & SHIFT) (Direct VM Migration Ready)" ), TRUE, "" )} -> REHOST (LIFT & SHIFT) (Direct VM Migration Ready) | G7: Medium
A8: Compute & Operating System Fit: | B8: (Resource Utilization Density) | C8: A) Zombie Workload: Consistently runs at less than 5% CPU/RAM capacity but requires an entire dedicated physical host due to legacy isolation fears. B) Highly Inefficient Static: Sized for historical peak loads that occur once a year; runs vastly over-provisioned during 95% of standard operating hours. C) Measured & Sized: Resource profiles are well-documented; can be mapped directly to equivalent, right-sized cloud instances based on actual usage metrics. D) Dynamic Resource Optimized: Memory and CPU are continuously dynamically allocated and tightly packed across shared cluster nodes using orchestrators like Kubernetes. | D8: D | E8: {=_xlfn.IFS(D8="A", 1, D8="B", 2, D8="C", 3, D8="D", 4, TRUE, 0)} -> 4 | F8: {=_xlfn.IFS( E8=1, _xlfn.IFS( A8="Security, Identity & Compliance", "RETAIN (Critical Legal/Sovereignty Roadblock)", A8="Compute & Operating System Fit", "RETIRE / SCRAP (Obsolete Hardware/OS Profile)", TRUE, "RETAIN (Fatal System/Dependency Blocker)" ), E8=2, _xlfn.IFS( A8="Software Lifecycle & Maintainability", "REFACTOR (Deep Code Rewrite Required)", A8="Compute & Operating System Fit", "RELOCATE (Lift-to-Cloud VMware/Hypervisor Cluster)", TRUE, "REFACTOR / RE-ARCHITECT (High Migration Debt)" ), E8=3, _xlfn.IFS( A8="Data & Storage Tier Compatibility", "REPLATFORM (Swap to Managed Cloud DB / Object Store)", A8="Networking, Integration & Performance", "REPLATFORM (Swap to Cloud ALB / CloudFront CDN)", TRUE, "REPLATFORM / LIFT-AND-SHAPE" ), E8=4, _xlfn.IFS( A8="Software Lifecycle & Maintainability", "REPURCHASE (Replace with Turnkey SaaS Product)", TRUE, "REHOST (LIFT & SHIFT) (Direct VM Migration Ready)" ), TRUE, "" )} -> REHOST (LIFT & SHIFT) (Direct VM Migration Ready) | G8: Large
A9: Compute & Operating System Fit: | B9: (Local File System Reliance) | C9: A) Persistent Local State: Writes critical application state, transaction logs, and persistent files directly to local, non-shareable root server disks. B) Local Shared Directory: Relies on local file path mappings but can survive if shifted onto high-availability network shares, though requires manual configuration. C) Ephemeral Local Storage: Uses local drives purely for temporary caching or transient scratch space; loss of local data does not break app integrity. D) Cloud-Storage Decoupled: Entirely decoupled from physical disks; reads and writes all persistent data directly to object storage or managed database endpoints. | D9: D | E9: {=_xlfn.IFS(D9="A", 1, D9="B", 2, D9="C", 3, D9="D", 4, TRUE, 0)} -> 4 | F9: {=_xlfn.IFS( E9=1, _xlfn.IFS( A9="Security, Identity & Compliance", "RETAIN (Critical Legal/Sovereignty Roadblock)", A9="Compute & Operating System Fit", "RETIRE / SCRAP (Obsolete Hardware/OS Profile)", TRUE, "RETAIN (Fatal System/Dependency Blocker)" ), E9=2, _xlfn.IFS( A9="Software Lifecycle & Maintainability", "REFACTOR (Deep Code Rewrite Required)", A9="Compute & Operating System Fit", "RELOCATE (Lift-to-Cloud VMware/Hypervisor Cluster)", TRUE, "REFACTOR / RE-ARCHITECT (High Migration Debt)" ), E9=3, _xlfn.IFS( A9="Data & Storage Tier Compatibility", "REPLATFORM (Swap to Managed Cloud DB / Object Store)", A9="Networking, Integration & Performance", "REPLATFORM (Swap to Cloud ALB / CloudFront CDN)", TRUE, "REPLATFORM / LIFT-AND-SHAPE" ), E9=4, _xlfn.IFS( A9="Software Lifecycle & Maintainability", "REPURCHASE (Replace with Turnkey SaaS Product)", TRUE, "REHOST (LIFT & SHIFT) (Direct VM Migration Ready)" ), TRUE, "" )} -> REHOST (LIFT & SHIFT) (Direct VM Migration Ready) | G9: Medium
A10: Data & Storage Tier Compatibility : | B10: (Database Paradigm) | C10: A) Proprietary Flat File: Uses legacy, non-relational database formats (e.g., ISAM, FoxPro, or Microsoft Access files) sitting on a local folder path. B) Heavy Custom Relational: Relies on a heavily modified commercial database engine (e.g., legacy Oracle or custom SQL Server setups) featuring massive database-layer logic. C) Standard Managed Relational: Standard SQL structure (PostgreSQL, MySQL, standard MS SQL) cleanly migratable to fully managed cloud database offerings. D) Distributed Cloud NoSQL/NewSQL: Engineered to utilize massively scalable, globally distributed NoSQL database fabrics (e.g., DynamoDB, CosmosDB) or cloud-native data networks. | D10: D | E10: {=_xlfn.IFS(D10="A", 1, D10="B", 2, D10="C", 3, D10="D", 4, TRUE, 0)} -> 4 | F10: {=_xlfn.IFS( E10=1, _xlfn.IFS( A10="Security, Identity & Compliance", "RETAIN (Critical Legal/Sovereignty Roadblock)", A10="Compute & Operating System Fit", "RETIRE / SCRAP (Obsolete Hardware/OS Profile)", TRUE, "RETAIN (Fatal System/Dependency Blocker)" ), E10=2, _xlfn.IFS( A10="Software Lifecycle & Maintainability", "REFACTOR (Deep Code Rewrite Required)", A10="Compute & Operating System Fit", "RELOCATE (Lift-to-Cloud VMware/Hypervisor Cluster)", TRUE, "REFACTOR / RE-ARCHITECT (High Migration Debt)" ), E10=3, _xlfn.IFS( A10="Data & Storage Tier Compatibility", "REPLATFORM (Swap to Managed Cloud DB / Object Store)", A10="Networking, Integration & Performance", "REPLATFORM (Swap to Cloud ALB / CloudFront CDN)", TRUE, "REPLATFORM / LIFT-AND-SHAPE" ), E10=4, _xlfn.IFS( A10="Software Lifecycle & Maintainability", "REPURCHASE (Replace with Turnkey SaaS Product)", TRUE, "REHOST (LIFT & SHIFT) (Direct VM Migration Ready)" ), TRUE, "" )} -> REHOST (LIFT & SHIFT) (Direct VM Migration Ready) | G10: Medium
A11: Data & Storage Tier Compatibility : | B11: (Database Extensions) | C11: A) Monolithic Stored Procedures: Core business logic is entirely written inside database-layer triggers, custom C-extensions, and thousands of lines of proprietary PL/SQL code. B) Extension Fragmented: Relies on specialized third-party database plugins or specific collation settings that restrict choices to unmanaged cloud VMs. C) Clean Standard Schemas: Database utilizes clean, ANSI-compliant SQL schemas; data logic is handled cleanly at the application code layer instead of the database. D) Polyglot-Ready Data Mesh: Uses micro-databases optimized per function, communicating cleanly via standardized REST/GraphQL endpoints with no direct cross-database links | D11: D | E11: {=_xlfn.IFS(D11="A", 1, D11="B", 2, D11="C", 3, D11="D", 4, TRUE, 0)} -> 4 | F11: {=_xlfn.IFS( E11=1, _xlfn.IFS( A11="Security, Identity & Compliance", "RETAIN (Critical Legal/Sovereignty Roadblock)", A11="Compute & Operating System Fit", "RETIRE / SCRAP (Obsolete Hardware/OS Profile)", TRUE, "RETAIN (Fatal System/Dependency Blocker)" ), E11=2, _xlfn.IFS( A11="Software Lifecycle & Maintainability", "REFACTOR (Deep Code Rewrite Required)", A11="Compute & Operating System Fit", "RELOCATE (Lift-to-Cloud VMware/Hypervisor Cluster)", TRUE, "REFACTOR / RE-ARCHITECT (High Migration Debt)" ), E11=3, _xlfn.IFS( A11="Data & Storage Tier Compatibility", "REPLATFORM (Swap to Managed Cloud DB / Object Store)", A11="Networking, Integration & Performance", "REPLATFORM (Swap to Cloud ALB / CloudFront CDN)", TRUE, "REPLATFORM / LIFT-AND-SHAPE" ), E11=4, _xlfn.IFS( A11="Software Lifecycle & Maintainability", "REPURCHASE (Replace with Turnkey SaaS Product)", TRUE, "REHOST (LIFT & SHIFT) (Direct VM Migration Ready)" ), TRUE, "" )} -> REHOST (LIFT & SHIFT) (Direct VM Migration Ready) | G11: Medium
A12: Data & Storage Tier Compatibility : | B12: (Storage Protocols) | C12: A) Fiber Channel SAN Bound: Requires sub-millisecond physical Fiber Channel SAN attachments with specific hardware block sizes to function without crashing. B) Legacy NAS Dependent: Requires local network shared file protocols (e.g., SMB v1/v2, NFS v3) with rigid posix-compliance requirements. C) Cloud Network Storage Ready: Compatible with standard cloud-managed file shares (e.g., AWS EFS, Azure Files) or standard scalable cloud block volumes. D) Object Native API: Connects directly via standard HTTPS API protocols to cloud object storage systems (e.g., S3/Blob) for all document and data lifecycle needs | D12: D | E12: {=_xlfn.IFS(D12="A", 1, D12="B", 2, D12="C", 3, D12="D", 4, TRUE, 0)} -> 4 | F12: {=_xlfn.IFS( E12=1, _xlfn.IFS( A12="Security, Identity & Compliance", "RETAIN (Critical Legal/Sovereignty Roadblock)", A12="Compute & Operating System Fit", "RETIRE / SCRAP (Obsolete Hardware/OS Profile)", TRUE, "RETAIN (Fatal System/Dependency Blocker)" ), E12=2, _xlfn.IFS( A12="Software Lifecycle & Maintainability", "REFACTOR (Deep Code Rewrite Required)", A12="Compute & Operating System Fit", "RELOCATE (Lift-to-Cloud VMware/Hypervisor Cluster)", TRUE, "REFACTOR / RE-ARCHITECT (High Migration Debt)" ), E12=3, _xlfn.IFS( A12="Data & Storage Tier Compatibility", "REPLATFORM (Swap to Managed Cloud DB / Object Store)", A12="Networking, Integration & Performance", "REPLATFORM (Swap to Cloud ALB / CloudFront CDN)", TRUE, "REPLATFORM / LIFT-AND-SHAPE" ), E12=4, _xlfn.IFS( A12="Software Lifecycle & Maintainability", "REPURCHASE (Replace with Turnkey SaaS Product)", TRUE, "REHOST (LIFT & SHIFT) (Direct VM Migration Ready)" ), TRUE, "" )} -> REHOST (LIFT & SHIFT) (Direct VM Migration Ready) | G12: Medium
A13: Data & Storage Tier Compatibility : | B13: (Data Volume (Size)) | C13: A) Massive Monolithic PB: Total dataset size exceeds 500 Terabytes to multiple Petabytes, making online network transfer over standard pipes mathematically impossible. B) Large TB Scale: Dataset is between 10TB and 100TB; can be transferred online but requires dedicated network line throttling and long migration windows. C) Moderate GB Scale: Dataset is under 1 Terabyte; easily syncs to the cloud over a standard internet or VPN pipe within a few hours. D) Lightweight Dynamic: Miniscule data storage profile; data structures are highly compact, modularized, and can be initialized anywhere instantly. | D13: D | E13: {=_xlfn.IFS(D13="A", 1, D13="B", 2, D13="C", 3, D13="D", 4, TRUE, 0)} -> 4 | F13: {=_xlfn.IFS( E13=1, _xlfn.IFS( A13="Security, Identity & Compliance", "RETAIN (Critical Legal/Sovereignty Roadblock)", A13="Compute & Operating System Fit", "RETIRE / SCRAP (Obsolete Hardware/OS Profile)", TRUE, "RETAIN (Fatal System/Dependency Blocker)" ), E13=2, _xlfn.IFS( A13="Software Lifecycle & Maintainability", "REFACTOR (Deep Code Rewrite Required)", A13="Compute & Operating System Fit", "RELOCATE (Lift-to-Cloud VMware/Hypervisor Cluster)", TRUE, "REFACTOR / RE-ARCHITECT (High Migration Debt)" ), E13=3, _xlfn.IFS( A13="Data & Storage Tier Compatibility", "REPLATFORM (Swap to Managed Cloud DB / Object Store)", A13="Networking, Integration & Performance", "REPLATFORM (Swap to Cloud ALB / CloudFront CDN)", TRUE, "REPLATFORM / LIFT-AND-SHAPE" ), E13=4, _xlfn.IFS( A13="Software Lifecycle & Maintainability", "REPURCHASE (Replace with Turnkey SaaS Product)", TRUE, "REHOST (LIFT & SHIFT) (Direct VM Migration Ready)" ), TRUE, "" )} -> REHOST (LIFT & SHIFT) (Direct VM Migration Ready) | G13: Medium
... A49: Commercial, Legal & Operational Readiness: | B49: (Commercial, Legal & Operational Readiness) | C49: A) Absentee Ownership: The application has no assigned business product owner; it is treated as a generic, forgotten IT server asset that nobody in the business claims responsibility for. B) Resistant Stakeholder: The business product owner is actively resistant to the cloud, fearing that a migration will disrupt their users, change layouts, or alter their established software schedules. C) Engaged Partner: The business owner is highly supportive of the migration, actively attends alignment syncs, and is willing to allocate business testing resources to validate the cloud environment. D) Strategy Champion: The product owner is actively driving the cloud transition to unlock specific commercial competitive advantages, like accelerated product release cycles or international market scaling. | D49: A | E49: {=_xlfn.IFS(D49="A", 1, D49="B", 2, D49="C", 3, D49="D", 4, TRUE, 0)} -> 1 | F49: {=_xlfn.IFS( E49=1, _xlfn.IFS( A49="Security, Identity & Compliance", "RETAIN (Critical Legal/Sovereignty Roadblock)", A49="Compute & Operating System Fit", "RETIRE / SCRAP (Obsolete Hardware/OS Profile)", TRUE, "RETAIN (Fatal System/Dependency Blocker)" ), E49=2, _xlfn.IFS( A49="Software Lifecycle & Maintainability", "REFACTOR (Deep Code Rewrite Required)", A49="Compute & Operating System Fit", "RELOCATE (Lift-to-Cloud VMware/Hypervisor Cluster)", TRUE, "REFACTOR / RE-ARCHITECT (High Migration Debt)" ), E49=3, _xlfn.IFS( A49="Data & Storage Tier Compatibility", "REPLATFORM (Swap to Managed Cloud DB / Object Store)", A49="Networking, Integration & Performance", "REPLATFORM (Swap to Cloud ALB / CloudFront CDN)", TRUE, "REPLATFORM / LIFT-AND-SHAPE" ), E49=4, _xlfn.IFS( A49="Software Lifecycle & Maintainability", "REPURCHASE (Replace with Turnkey SaaS Product)", TRUE, "REHOST (LIFT & SHIFT) (Direct VM Migration Ready)" ), TRUE, "" )} -> RETAIN (Fatal System/Dependency Blocker) | G49: Small
B51: © 2026 Amit Kulkarni All rights reserved

Sheet Dashboards
A1: CRA Domain Perspective | B1: Average Score | C1: Result
A2: Compute & Operating System Fit: | B2: =AVERAGEIF(Inputs!A:A, A2, Inputs!E:E) -> 4
A3: Data & Storage Tier Compatibility : | B3: =AVERAGEIF(Inputs!A:A, A3, Inputs!E:E) -> 4
A4: Networking, Integration & Performance: | B4: =AVERAGEIF(Inputs!A:A, A4, Inputs!E:E) -> 4
A5: Security, Identity & Compliance: | B5: =AVERAGEIF(Inputs!A:A, A5, Inputs!E:E) -> 2.75
A6: Software Lifecycle & Maintainability : | B6: =AVERAGEIF(Inputs!A:A, A6, Inputs!E:E) -> 3.125
A7: Commercial, Legal & Operational Readiness: | B7: =AVERAGEIF(Inputs!A:A, A7, Inputs!E:E) -> 2
C8: Master 7-R Strategy Selector
C9: {=_xlfn.IFS( COUNTIF(Inputs!E2:E48, 1) > 12, "STRATEGY: MULTI-TIER RETAIN & RETIRE BLOCK (Portfolio exhibits terminal technical debt. Immediate freeze.)", COUNTIF(Inputs!F2:F48, "*RETAIN*") > 0, "STRATEGY: HYBRID RETAIN (Workload is cloud-compatible but blocked by localized Compliance or Data Sovereignty mandates.)", COUNTIF(Inputs!F2:F48, "*RELOCATE*") > 0, "STRATEGY: HYBRID RELOCATE (Workload features nested virtualization dependencies. Route directly to AWS/Azure VMware Solution.)", AVERAGE(Inputs!E2:E48) >= 3.5, "STRATEGY: COMPREHENSIVE REFACTOR (Ideal candidate for an immediate, high-velocity cloud-native container or serverless migration.)", AVERAGE(Inputs!E2:E48) >= 2.8, "STRATEGY: CORE REHOST (Workload runtime profiles are stable and standard. Deploy automated replication agents for a rapid Lift-and-Shift.)", AVERAGE(Inputs!E2:E48) >= 2, "STRATEGY: TARGETED REPLATFORM (Execute migration but immediately offload operational overhead to cloud-managed databases and shared files.)", TRUE, "STRATEGY: COMPLETE REPURCHASE (Workload is severely unoptimized for cloud IaaS. Decommission internal code and procure a standard third-party SaaS alternative.)" )} -> STRATEGY: CORE REHOST (Workload runtime profiles are stable and standard. Deploy automated replication agents for a rapid Lift-and-Shift.)
A27: © 2026 Amit Kulkarni All rights reserved
