Workbook

Sheet Platform_DB
A1: Vendor Name | B1: Market Share & Industry Presence | C1: Pricing Models & Transparency | D1: Global Data Center Footprint | E1: Compliance & Security | F1: Hybrid Cloud Capabilities | G1: Enterprise Agreements & Licensing Flexibilities | H1: DevOps Integration | I1: Global Network Infrastructure & Performance | J1: Latency, Throughput & Scalability | K1: Failover & High Availability | L1: Vendor Lock-in & Portability | M1: Management & Monitoring Tools | N1: Cost Management & Optimization | O1: Storage Performance & IOPS | P1: Total Cost of Ownership (TCO) Analysis | Q1: Data Transfer & Egress Cost | R1: Network Security & Firewalls | S1: AI/ML Platform Capabilities | T1: Data Analytics & Big Data | U1: Customer Support & SLA Levels | V1: Developer Ecosystem & Community
A2: AWS | B2: 1 | C2: 0.7 | D2: 1 | E2: 1 | F2: 0.8 | G2: 0.7 | H2: 1 | I2: 1 | J2: 1 | K2: 1 | L2: 0.5 | M2: 0.9 | N2: 0.8 | O2: 0.9 | P2: 0.8 | Q2: 0.6 | R2: 0.9 | S2: 1 | T2: 1 | U2: 0.8 | V2: 1
A3: Azure | B3: 0.9 | C3: 0.8 | D3: 1 | E3: 1 | F3: 1 | G3: 1 | H3: 0.9 | I3: 0.9 | J3: 0.9 | K3: 0.9 | L3: 0.6 | M3: 0.9 | N3: 0.8 | O3: 0.9 | P3: 0.9 | Q3: 0.7 | R3: 0.9 | S3: 0.9 | T3: 0.9 | U3: 0.9 | V3: 0.9
A4: GCP | B4: 0.8 | C4: 0.9 | D4: 0.8 | E4: 0.9 | F4: 0.8 | G4: 0.8 | H4: 1 | I4: 1 | J4: 0.9 | K4: 0.9 | L4: 0.8 | M4: 0.8 | N4: 0.9 | O4: 0.8 | P4: 0.8 | Q4: 0.8 | R4: 0.9 | S4: 1 | T4: 1 | U4: 0.8 | V4: 0.8
A5: OCI | B5: 0.6 | C5: 1 | D5: 0.7 | E5: 0.9 | F5: 0.7 | G5: 0.9 | H5: 0.7 | I5: 0.9 | J5: 0.9 | K5: 0.8 | L5: 0.7 | M5: 0.7 | N5: 0.8 | O5: 1 | P5: 1 | Q5: 0.9 | R5: 0.8 | S5: 0.7 | T5: 0.7 | U5: 0.8 | V5: 0.6
A6: IBM | B6: 0.5 | C6: 0.7 | D6: 0.7 | E6: 1 | F6: 0.9 | G6: 0.8 | H6: 0.7 | I6: 0.7 | J6: 0.7 | K6: 0.8 | L6: 0.7 | M6: 0.7 | N6: 0.7 | O6: 0.7 | P6: 0.8 | Q6: 0.7 | R6: 0.8 | S6: 0.6 | T6: 0.7 | U6: 0.9 | V6: 0.6
A7: Alibaba | B7: 0.6 | C7: 0.8 | D7: 0.8 | E7: 0.7 | F7: 0.7 | G7: 0.7 | H7: 0.7 | I7: 0.8 | J7: 0.8 | K7: 0.8 | L7: 0.5 | M7: 0.7 | N7: 0.7 | O7: 0.8 | P7: 0.7 | Q7: 0.8 | R7: 0.7 | S7: 0.7 | T7: 0.8 | U7: 0.7 | V7: 0.6
A9: © 2026 Amit Kulkarni. All rights reserved.

Sheet User_Responses
A1: # | B1: Category | C1: Client-Specific Question | D1: User Priority | E1: User Score | F1: Weight Priority Low - 1 High - 5 | G1: Client Target Scores | H1: Normalized Weight
A2: 1 | B2: Market Share & Industry Presence | C2: What is your organization’s stance on vendor market dominance? a) We prefer niche, specialized players regardless of market share. b) We accept emerging vendors with stable financial backing. c) We prefer top-tier established vendors with a strong roadmap. d) We strictly require a top 3 market-dominant leader. | D2: c | E2: {=_xlfn.SWITCH(D2,"d",1,"c",0.75,"b",0.5,"a", 0.25)} -> 0.75 | F2: 4 | G2: =AVERAGEIF(B$2:$B$66, B2, $E$2:$E$66) -> 0.58333333 | H2: =SUMIF($B$2:$B$66, B2, $F$2:$F$66) / SUM(F$2:$F$66) -> 0.051643192
A3: 2 | B3: Market Share & Industry Presence | C3: How critical is third-party vendor tool ecosystem support? a) Not critical; we build most integrations in-house. b) Minimal; we only need a few basic tool integrations. c) Important; we rely on mainstream third-party software tools. d) Mission-critical; we require universal ecosystem compatibility. | D3: b | E3: {=_xlfn.SWITCH(D3,"d",1,"c",0.75,"b",0.5,"a", 0.25)} -> 0.5 | F3: 4 | G3: =AVERAGEIF(B$2:$B$66, B3, $E$2:$E$66) -> 0.58333333 | H3: =SUMIF($B$2:$B$66, B3, $F$2:$F$66) / SUM(F$2:$F$66) -> 0.051643192
A4: 3 | B4: Pricing Models & Transparency | C4: What is your preferred cloud billing model? a) Fixed monthly billing with minimal tracking tools. b) Pay-as-you-go with basic cost visibility. c) Tiered pricing with granular billing API access. d) Predictive, fully transparent pricing with real-time anomalies. | D4: d | E4: {=_xlfn.SWITCH(D4,"d",1,"c",0.75,"b",0.5,"a", 0.25)} -> 1 | F4: 3 | G4: =AVERAGEIF(B$2:$B$66, B4, $E$2:$E$66) -> 0.66666667 | H4: =SUMIF($B$2:$B$66, B4, $F$2:$F$66) / SUM(F$2:$F$66) -> 0.051643192
A5: 4 | B5: Pricing Models & Transparency | C5: How complex is your required discounting structure? a) No long-term commitments; pure on-demand usage. b) Basic 1-year commitments for predictable workloads. c) Multi-year commitments with flexible compute exchange rights. d) Complex, multi-product customized enterprise billing discounts. | D5: b | E5: {=_xlfn.SWITCH(D5,"d",1,"c",0.75,"b",0.5,"a", 0.25)} -> 0.5 | F5: 3 | G5: =AVERAGEIF(B$2:$B$66, B5, $E$2:$E$66) -> 0.66666667 | H5: =SUMIF($B$2:$B$66, B5, $F$2:$F$66) / SUM(F$2:$F$66) -> 0.051643192
A6: 5 | B6: Global Data Center Footprint | C6: What are your geographical data residency requirements? a) Single local region; no global presence needed. b) Regional presence across a single continent. c) Multi-continental presence across primary business hubs. d) Hyper-distributed presence including emerging global markets. | D6: b | E6: {=_xlfn.SWITCH(D6,"d",1,"c",0.75,"b",0.5,"a", 0.25)} -> 0.5 | F6: 4 | G6: =AVERAGEIF(B$2:$B$66, B6, $E$2:$E$66) -> 0.5 | H6: =SUMIF($B$2:$B$66, B6, $F$2:$F$66) / SUM(F$2:$F$66) -> 0.056338028
A7: 6 | B7: Global Data Center Footprint | C7: How critical is proximity to specific localized edge locations? a) Not required; standard cloud regions are sufficient. b) Nice to have for localized testing and low traffic. c) Required for content delivery networks in main cities. d) Critical for real-time edge processing near field operations. | D7: b | E7: {=_xlfn.SWITCH(D7,"d",1,"c",0.75,"b",0.5,"a", 0.25)} -> 0.5 | F7: 5 | G7: =AVERAGEIF(B$2:$B$66, B7, $E$2:$E$66) -> 0.5 | H7: =SUMIF($B$2:$B$66, B7, $F$2:$F$66) / SUM(F$2:$F$66) -> 0.056338028
A8: 7 | B8: Compliance & Security | C8: What industry-specific compliance certifications do you require? a) Standard commercial security protocols only. b) Basic regional certifications (e.g., local data privacy). c) Standard industry frameworks (e.g., SOC2, ISO 27001). d) High-stringency certifications (e.g., HIPAA, FedRAMP, PCI-DSS). | D8: b | E8: {=_xlfn.SWITCH(D8,"d",1,"c",0.75,"b",0.5,"a", 0.25)} -> 0.5 | F8: 3 | G8: =AVERAGEIF(B$2:$B$66, B8, $E$2:$E$66) -> 0.66666667 | H8: =SUMIF($B$2:$B$66, B8, $F$2:$F$66) / SUM(F$2:$F$66) -> 0.042253521
A9: 8 | B9: Compliance & Security | C9: What level of sovereign data isolation does your client require? a) No restrictions on public cloud shared infrastructure. b) Logical separation of data within shared infrastructure. c) Dedicated hardware instances in public zones. d) Complete digital and physical sovereignty in isolated regions. | D9: d | E9: {=_xlfn.SWITCH(D9,"d",1,"c",0.75,"b",0.5,"a", 0.25)} -> 1 | F9: 3 | G9: =AVERAGEIF(B$2:$B$66, B9, $E$2:$E$66) -> 0.66666667 | H9: =SUMIF($B$2:$B$66, B9, $F$2:$F$66) / SUM(F$2:$F$66) -> 0.042253521
A10: 9 | B10: Hybrid Cloud Capabilities | C10: What is the planned architecture for your legacy on-premises assets? a) Complete migration to cloud; no hybrid footprint remains. b) Lift-and-shift to cloud with temporary legacy connections. c) Long-term hybrid setup with separate management planes. d) Seamless, unified hybrid control plane across on-prem and cloud. | D10: c | E10: {=_xlfn.SWITCH(D10,"d",1,"c",0.75,"b",0.5,"a", 0.25)} -> 0.75 | F10: 4 | G10: =AVERAGEIF(B$2:$B$66, B10, $E$2:$E$66) -> 0.5 | H10: =SUMIF($B$2:$B$66, B10, $F$2:$F$66) / SUM(F$2:$F$66) -> 0.03286385
A11: 10 | B11: Hybrid Cloud Capabilities | C11: How do you plan to extend cloud services to your local hardware? a) We do not need cloud services on physical on-prem hardware. b) Basic software agents monitoring on-premises servers. c) Virtual appliances deployed on local virtualization platforms. d) Native vendor hardware extensions (e.g., Outposts, Azure Stack). | D11: a | E11: {=_xlfn.SWITCH(D11,"d",1,"c",0.75,"b",0.5,"a", 0.25)} -> 0.25 | F11: 3 | G11: =AVERAGEIF(B$2:$B$66, B11, $E$2:$E$66) -> 0.5 | H11: =SUMIF($B$2:$B$66, B11, $F$2:$F$66) / SUM(F$2:$F$66) -> 0.03286385
A12: 11 | B12: Enterprise Agreements & Licensing Flexibilities | C12: How do you plan to manage existing software licenses (e.g., Windows, Oracle)? a) Abandon existing licenses and buy everything cloud-native. b) Manual migration of eligible licenses with complex tracking. c) Semi-automated bring-your-own-license (BYOL) frameworks. d) Fully automated, financially optimized BYOL programs. | D12: d | E12: {=_xlfn.SWITCH(D12,"d",1,"c",0.75,"b",0.5,"a", 0.25)} -> 1 | F12: 4 | G12: =AVERAGEIF(B$2:$B$66, B12, $E$2:$E$66) -> 0.75 | H12: =SUMIF($B$2:$B$66, B12, $F$2:$F$66) / SUM(F$2:$F$66) -> 0.046948357
A13: 12 | B13: Enterprise Agreements & Licensing Flexibilities | C13: What level of contract flexibility do you require for minimum spend commits? a) No minimum commit; we pay higher variable rates willingly. b) Fixed annual spend with rigid product allocations. c) Flexible spend commitments with annual re-baselining. d) Fully fluid cross-product spend shifting with no penalties. | D13: c | E13: {=_xlfn.SWITCH(D13,"d",1,"c",0.75,"b",0.5,"a", 0.25)} -> 0.75 | F13: 3 | G13: =AVERAGEIF(B$2:$B$66, B13, $E$2:$E$66) -> 0.75 | H13: =SUMIF($B$2:$B$66, B13, $F$2:$F$66) / SUM(F$2:$F$66) -> 0.046948357
... A66: 65 | B66: Data Transfer & Egress Cost | C66: What is your policy or requirement regarding Cloud Egress Fee Waivers? a) Egress fees are minor; we don't need a formal waiver agreement. b) We try to design architecture carefully to minimize egress naturally. c) We require a contract that caps or drops egress costs if migrating from a rival cloud. d) Non-negotiable requirement for 100% zero-egress pricing models or dedicated enterprise waivers. | D66: b | E66: {=_xlfn.SWITCH(D66,"d",1,"c",0.75,"b",0.5,"a", 0.25)} -> 0.5 | F66: 3 | G66: =AVERAGEIF(B$2:$B$66, B66, $E$2:$E$66) -> 0.5 | H66: =SUMIF($B$2:$B$66, B66, $F$2:$F$66) / SUM(F$2:$F$66) -> 0.014084507
B68: © 2026 Amit Kulkarni. All rights reserved.

Sheet Vendor_Rankings
A1: Category | B1: Client Target Scores | C1: Normalized Weight | D1: AWS | E1: AWS Fit | F1: Azure | G1: Azure Fit | H1: GCP | I1: GCP Fit | J1: OCI | K1: OCI Fit | L1: IBM | M1: IBM Fit | N1: Alibaba | O1: Alibaba Fit
A2: Market Share & Industry Presence | B2: =AVERAGEIF(User_Responses!$B$2:$B$66, A2, User_Responses!$G$2:$G$66) -> 0.58333333 | C2: =SUMIF(User_Responses!$B$2:$B$66, A2, User_Responses!$H$2:$H$66) / SUM(User_Responses!H$2:$H$66) -> 0.062857143 | D2: =_xlfn.XLOOKUP(A2, Platform_DB!$B$1:$Z$1, Platform_DB!$B$2:$Z$2) -> 1 | E2: =1-ABS(B2-D2) -> 0.58333333 | F2: =_xlfn.XLOOKUP(A2, Platform_DB!$B$1:$Z$1, Platform_DB!$B$3:$Z$3) -> 0.9 | G2: =1-ABS(B2-F2) -> 0.68333333 | H2: =_xlfn.XLOOKUP(A2, Platform_DB!$B$1:$Z$1, Platform_DB!$B$4:$Z$4) -> 0.8 | I2: =1-ABS(B2-H2) -> 0.78333333 | J2: =_xlfn.XLOOKUP(A2, Platform_DB!$B$1:$Z$1, Platform_DB!$B$5:$Z$5) -> 0.6 | K2: =1-ABS(B2-J2) -> 0.98333333 | L2: =_xlfn.XLOOKUP(A2, Platform_DB!$B$1:$Z$1, Platform_DB!$B$6:$Z$6) -> 0.5 | M2: =1-ABS(B2-L2) -> 0.91666667 | N2: =_xlfn.XLOOKUP(A2, Platform_DB!$B$1:$Z$1, Platform_DB!$B$7:$Z$7) -> 0.6 | O2: =1-ABS(B2-N2) -> 0.98333333
A3: Pricing Models & Transparency | B3: =AVERAGEIF(User_Responses!$B$2:$B$66, A3, User_Responses!$G$2:$G$66) -> 0.66666667 | C3: =SUMIF(User_Responses!$B$2:$B$66, A3, User_Responses!$H$2:$H$66) / SUM(User_Responses!H$2:$H$66) -> 0.062857143 | D3: =_xlfn.XLOOKUP(A3, Platform_DB!$B$1:$Z$1, Platform_DB!$B$2:$Z$2) -> 0.7 | E3: =1-ABS(B3-D3) -> 0.96666667 | F3: =_xlfn.XLOOKUP(A3, Platform_DB!$B$1:$Z$1, Platform_DB!$B$3:$Z$3) -> 0.8 | G3: =1-ABS(B3-F3) -> 0.86666667 | H3: =_xlfn.XLOOKUP(A3, Platform_DB!$B$1:$Z$1, Platform_DB!$B$4:$Z$4) -> 0.9 | I3: =1-ABS(B3-H3) -> 0.76666667 | J3: =_xlfn.XLOOKUP(A3, Platform_DB!$B$1:$Z$1, Platform_DB!$B$5:$Z$5) -> 1 | K3: =1-ABS(B3-J3) -> 0.66666667 | L3: =_xlfn.XLOOKUP(A3, Platform_DB!$B$1:$Z$1, Platform_DB!$B$6:$Z$6) -> 0.7 | M3: =1-ABS(B3-L3) -> 0.96666667 | N3: =_xlfn.XLOOKUP(A3, Platform_DB!$B$1:$Z$1, Platform_DB!$B$7:$Z$7) -> 0.8 | O3: =1-ABS(B3-N3) -> 0.86666667
A4: Global Data Center Footprint | B4: =AVERAGEIF(User_Responses!$B$2:$B$66, A4, User_Responses!$G$2:$G$66) -> 0.5 | C4: =SUMIF(User_Responses!$B$2:$B$66, A4, User_Responses!$H$2:$H$66) / SUM(User_Responses!H$2:$H$66) -> 0.068571429 | D4: =_xlfn.XLOOKUP(A4, Platform_DB!$B$1:$Z$1, Platform_DB!$B$2:$Z$2) -> 1 | E4: =1-ABS(B4-D4) -> 0.5 | F4: =_xlfn.XLOOKUP(A4, Platform_DB!$B$1:$Z$1, Platform_DB!$B$3:$Z$3) -> 1 | G4: =1-ABS(B4-F4) -> 0.5 | H4: =_xlfn.XLOOKUP(A4, Platform_DB!$B$1:$Z$1, Platform_DB!$B$4:$Z$4) -> 0.8 | I4: =1-ABS(B4-H4) -> 0.7 | J4: =_xlfn.XLOOKUP(A4, Platform_DB!$B$1:$Z$1, Platform_DB!$B$5:$Z$5) -> 0.7 | K4: =1-ABS(B4-J4) -> 0.8 | L4: =_xlfn.XLOOKUP(A4, Platform_DB!$B$1:$Z$1, Platform_DB!$B$6:$Z$6) -> 0.7 | M4: =1-ABS(B4-L4) -> 0.8 | N4: =_xlfn.XLOOKUP(A4, Platform_DB!$B$1:$Z$1, Platform_DB!$B$7:$Z$7) -> 0.8 | O4: =1-ABS(B4-N4) -> 0.7
A5: Compliance & Security | B5: =AVERAGEIF(User_Responses!$B$2:$B$66, A5, User_Responses!$G$2:$G$66) -> 0.66666667 | C5: =SUMIF(User_Responses!$B$2:$B$66, A5, User_Responses!$H$2:$H$66) / SUM(User_Responses!H$2:$H$66) -> 0.051428571 | D5: =_xlfn.XLOOKUP(A5, Platform_DB!$B$1:$Z$1, Platform_DB!$B$2:$Z$2) -> 1 | E5: =1-ABS(B5-D5) -> 0.66666667 | F5: =_xlfn.XLOOKUP(A5, Platform_DB!$B$1:$Z$1, Platform_DB!$B$3:$Z$3) -> 1 | G5: =1-ABS(B5-F5) -> 0.66666667 | H5: =_xlfn.XLOOKUP(A5, Platform_DB!$B$1:$Z$1, Platform_DB!$B$4:$Z$4) -> 0.9 | I5: =1-ABS(B5-H5) -> 0.76666667 | J5: =_xlfn.XLOOKUP(A5, Platform_DB!$B$1:$Z$1, Platform_DB!$B$5:$Z$5) -> 0.9 | K5: =1-ABS(B5-J5) -> 0.76666667 | L5: =_xlfn.XLOOKUP(A5, Platform_DB!$B$1:$Z$1, Platform_DB!$B$6:$Z$6) -> 1 | M5: =1-ABS(B5-L5) -> 0.66666667 | N5: =_xlfn.XLOOKUP(A5, Platform_DB!$B$1:$Z$1, Platform_DB!$B$7:$Z$7) -> 0.7 | O5: =1-ABS(B5-N5) -> 0.96666667
A6: Hybrid Cloud Capabilities | B6: =AVERAGEIF(User_Responses!$B$2:$B$66, A6, User_Responses!$G$2:$G$66) -> 0.5 | C6: =SUMIF(User_Responses!$B$2:$B$66, A6, User_Responses!$H$2:$H$66) / SUM(User_Responses!H$2:$H$66) -> 0.026666667 | D6: =_xlfn.XLOOKUP(A6, Platform_DB!$B$1:$Z$1, Platform_DB!$B$2:$Z$2) -> 0.8 | E6: =1-ABS(B6-D6) -> 0.7 | F6: =_xlfn.XLOOKUP(A6, Platform_DB!$B$1:$Z$1, Platform_DB!$B$3:$Z$3) -> 1 | G6: =1-ABS(B6-F6) -> 0.5 | H6: =_xlfn.XLOOKUP(A6, Platform_DB!$B$1:$Z$1, Platform_DB!$B$4:$Z$4) -> 0.8 | I6: =1-ABS(B6-H6) -> 0.7 | J6: =_xlfn.XLOOKUP(A6, Platform_DB!$B$1:$Z$1, Platform_DB!$B$5:$Z$5) -> 0.7 | K6: =1-ABS(B6-J6) -> 0.8 | L6: =_xlfn.XLOOKUP(A6, Platform_DB!$B$1:$Z$1, Platform_DB!$B$6:$Z$6) -> 0.9 | M6: =1-ABS(B6-L6) -> 0.6 | N6: =_xlfn.XLOOKUP(A6, Platform_DB!$B$1:$Z$1, Platform_DB!$B$7:$Z$7) -> 0.7 | O6: =1-ABS(B6-N6) -> 0.8
A7: Enterprise Agreements & Licensing Flexibilities | B7: =AVERAGEIF(User_Responses!$B$2:$B$66, A7, User_Responses!$G$2:$G$66) -> 0.75 | C7: =SUMIF(User_Responses!$B$2:$B$66, A7, User_Responses!$H$2:$H$66) / SUM(User_Responses!H$2:$H$66) -> 0.057142857 | D7: =_xlfn.XLOOKUP(A7, Platform_DB!$B$1:$Z$1, Platform_DB!$B$2:$Z$2) -> 0.7 | E7: =1-ABS(B7-D7) -> 0.95 | F7: =_xlfn.XLOOKUP(A7, Platform_DB!$B$1:$Z$1, Platform_DB!$B$3:$Z$3) -> 1 | G7: =1-ABS(B7-F7) -> 0.75 | H7: =_xlfn.XLOOKUP(A7, Platform_DB!$B$1:$Z$1, Platform_DB!$B$4:$Z$4) -> 0.8 | I7: =1-ABS(B7-H7) -> 0.95 | J7: =_xlfn.XLOOKUP(A7, Platform_DB!$B$1:$Z$1, Platform_DB!$B$5:$Z$5) -> 0.9 | K7: =1-ABS(B7-J7) -> 0.85 | L7: =_xlfn.XLOOKUP(A7, Platform_DB!$B$1:$Z$1, Platform_DB!$B$6:$Z$6) -> 0.8 | M7: =1-ABS(B7-L7) -> 0.95 | N7: =_xlfn.XLOOKUP(A7, Platform_DB!$B$1:$Z$1, Platform_DB!$B$7:$Z$7) -> 0.7 | O7: =1-ABS(B7-N7) -> 0.95
A8: DevOps Integration | B8: =AVERAGEIF(User_Responses!$B$2:$B$66, A8, User_Responses!$G$2:$G$66) -> 0.58333333 | C8: =SUMIF(User_Responses!$B$2:$B$66, A8, User_Responses!$H$2:$H$66) / SUM(User_Responses!H$2:$H$66) -> 0.057142857 | D8: =_xlfn.XLOOKUP(A8, Platform_DB!$B$1:$Z$1, Platform_DB!$B$2:$Z$2) -> 1 | E8: =1-ABS(B8-D8) -> 0.58333333 | F8: =_xlfn.XLOOKUP(A8, Platform_DB!$B$1:$Z$1, Platform_DB!$B$3:$Z$3) -> 0.9 | G8: =1-ABS(B8-F8) -> 0.68333333 | H8: =_xlfn.XLOOKUP(A8, Platform_DB!$B$1:$Z$1, Platform_DB!$B$4:$Z$4) -> 1 | I8: =1-ABS(B8-H8) -> 0.58333333 | J8: =_xlfn.XLOOKUP(A8, Platform_DB!$B$1:$Z$1, Platform_DB!$B$5:$Z$5) -> 0.7 | K8: =1-ABS(B8-J8) -> 0.88333333 | L8: =_xlfn.XLOOKUP(A8, Platform_DB!$B$1:$Z$1, Platform_DB!$B$6:$Z$6) -> 0.7 | M8: =1-ABS(B8-L8) -> 0.88333333 | N8: =_xlfn.XLOOKUP(A8, Platform_DB!$B$1:$Z$1, Platform_DB!$B$7:$Z$7) -> 0.7 | O8: =1-ABS(B8-N8) -> 0.88333333
A9: Global Network Infrastructure & Performance | B9: =AVERAGEIF(User_Responses!$B$2:$B$66, A9, User_Responses!$G$2:$G$66) -> 0.66666667 | C9: =SUMIF(User_Responses!$B$2:$B$66, A9, User_Responses!$H$2:$H$66) / SUM(User_Responses!H$2:$H$66) -> 0.057142857 | D9: =_xlfn.XLOOKUP(A9, Platform_DB!$B$1:$Z$1, Platform_DB!$B$2:$Z$2) -> 1 | E9: =1-ABS(B9-D9) -> 0.66666667 | F9: =_xlfn.XLOOKUP(A9, Platform_DB!$B$1:$Z$1, Platform_DB!$B$3:$Z$3) -> 0.9 | G9: =1-ABS(B9-F9) -> 0.76666667 | H9: =_xlfn.XLOOKUP(A9, Platform_DB!$B$1:$Z$1, Platform_DB!$B$4:$Z$4) -> 1 | I9: =1-ABS(B9-H9) -> 0.66666667 | J9: =_xlfn.XLOOKUP(A9, Platform_DB!$B$1:$Z$1, Platform_DB!$B$5:$Z$5) -> 0.9 | K9: =1-ABS(B9-J9) -> 0.76666667 | L9: =_xlfn.XLOOKUP(A9, Platform_DB!$B$1:$Z$1, Platform_DB!$B$6:$Z$6) -> 0.7 | M9: =1-ABS(B9-L9) -> 0.96666667 | N9: =_xlfn.XLOOKUP(A9, Platform_DB!$B$1:$Z$1, Platform_DB!$B$7:$Z$7) -> 0.8 | O9: =1-ABS(B9-N9) -> 0.86666667
A10: Latency, Throughput & Scalability | B10: =AVERAGEIF(User_Responses!$B$2:$B$66, A10, User_Responses!$G$2:$G$66) -> 0.83333333 | C10: =SUMIF(User_Responses!$B$2:$B$66, A10, User_Responses!$H$2:$H$66) / SUM(User_Responses!H$2:$H$66) -> 0.045714286 | D10: =_xlfn.XLOOKUP(A10, Platform_DB!$B$1:$Z$1, Platform_DB!$B$2:$Z$2) -> 1 | E10: =1-ABS(B10-D10) -> 0.83333333 | F10: =_xlfn.XLOOKUP(A10, Platform_DB!$B$1:$Z$1, Platform_DB!$B$3:$Z$3) -> 0.9 | G10: =1-ABS(B10-F10) -> 0.93333333 | H10: =_xlfn.XLOOKUP(A10, Platform_DB!$B$1:$Z$1, Platform_DB!$B$4:$Z$4) -> 0.9 | I10: =1-ABS(B10-H10) -> 0.93333333 | J10: =_xlfn.XLOOKUP(A10, Platform_DB!$B$1:$Z$1, Platform_DB!$B$5:$Z$5) -> 0.9 | K10: =1-ABS(B10-J10) -> 0.93333333 | L10: =_xlfn.XLOOKUP(A10, Platform_DB!$B$1:$Z$1, Platform_DB!$B$6:$Z$6) -> 0.7 | M10: =1-ABS(B10-L10) -> 0.86666667 | N10: =_xlfn.XLOOKUP(A10, Platform_DB!$B$1:$Z$1, Platform_DB!$B$7:$Z$7) -> 0.8 | O10: =1-ABS(B10-N10) -> 0.96666667
A11: Failover & High Availability | B11: =AVERAGEIF(User_Responses!$B$2:$B$66, A11, User_Responses!$G$2:$G$66) -> 0.58333333 | C11: =SUMIF(User_Responses!$B$2:$B$66, A11, User_Responses!$H$2:$H$66) / SUM(User_Responses!H$2:$H$66) -> 0.057142857 | D11: =_xlfn.XLOOKUP(A11, Platform_DB!$B$1:$Z$1, Platform_DB!$B$2:$Z$2) -> 1 | E11: =1-ABS(B11-D11) -> 0.58333333 | F11: =_xlfn.XLOOKUP(A11, Platform_DB!$B$1:$Z$1, Platform_DB!$B$3:$Z$3) -> 0.9 | G11: =1-ABS(B11-F11) -> 0.68333333 | H11: =_xlfn.XLOOKUP(A11, Platform_DB!$B$1:$Z$1, Platform_DB!$B$4:$Z$4) -> 0.9 | I11: =1-ABS(B11-H11) -> 0.68333333 | J11: =_xlfn.XLOOKUP(A11, Platform_DB!$B$1:$Z$1, Platform_DB!$B$5:$Z$5) -> 0.8 | K11: =1-ABS(B11-J11) -> 0.78333333 | L11: =_xlfn.XLOOKUP(A11, Platform_DB!$B$1:$Z$1, Platform_DB!$B$6:$Z$6) -> 0.8 | M11: =1-ABS(B11-L11) -> 0.78333333 | N11: =_xlfn.XLOOKUP(A11, Platform_DB!$B$1:$Z$1, Platform_DB!$B$7:$Z$7) -> 0.8 | O11: =1-ABS(B11-N11) -> 0.78333333
A12: Vendor Lock-in & Portability | B12: =AVERAGEIF(User_Responses!$B$2:$B$66, A12, User_Responses!$G$2:$G$66) -> 0.5 | C12: =SUMIF(User_Responses!$B$2:$B$66, A12, User_Responses!$H$2:$H$66) / SUM(User_Responses!H$2:$H$66) -> 0.074285714 | D12: =_xlfn.XLOOKUP(A12, Platform_DB!$B$1:$Z$1, Platform_DB!$B$2:$Z$2) -> 0.5 | E12: =1-ABS(B12-D12) -> 1 | F12: =_xlfn.XLOOKUP(A12, Platform_DB!$B$1:$Z$1, Platform_DB!$B$3:$Z$3) -> 0.6 | G12: =1-ABS(B12-F12) -> 0.9 | H12: =_xlfn.XLOOKUP(A12, Platform_DB!$B$1:$Z$1, Platform_DB!$B$4:$Z$4) -> 0.8 | I12: =1-ABS(B12-H12) -> 0.7 | J12: =_xlfn.XLOOKUP(A12, Platform_DB!$B$1:$Z$1, Platform_DB!$B$5:$Z$5) -> 0.7 | K12: =1-ABS(B12-J12) -> 0.8 | L12: =_xlfn.XLOOKUP(A12, Platform_DB!$B$1:$Z$1, Platform_DB!$B$6:$Z$6) -> 0.7 | M12: =1-ABS(B12-L12) -> 0.8 | N12: =_xlfn.XLOOKUP(A12, Platform_DB!$B$1:$Z$1, Platform_DB!$B$7:$Z$7) -> 0.5 | O12: =1-ABS(B12-N12) -> 1
A13: Management & Monitoring Tools | B13: =AVERAGEIF(User_Responses!$B$2:$B$66, A13, User_Responses!$G$2:$G$66) -> 1 | C13: =SUMIF(User_Responses!$B$2:$B$66, A13, User_Responses!$H$2:$H$66) / SUM(User_Responses!H$2:$H$66) -> 0.03047619 | D13: =_xlfn.XLOOKUP(A13, Platform_DB!$B$1:$Z$1, Platform_DB!$B$2:$Z$2) -> 0.9 | E13: =1-ABS(B13-D13) -> 0.9 | F13: =_xlfn.XLOOKUP(A13, Platform_DB!$B$1:$Z$1, Platform_DB!$B$3:$Z$3) -> 0.9 | G13: =1-ABS(B13-F13) -> 0.9 | H13: =_xlfn.XLOOKUP(A13, Platform_DB!$B$1:$Z$1, Platform_DB!$B$4:$Z$4) -> 0.8 | I13: =1-ABS(B13-H13) -> 0.8 | J13: =_xlfn.XLOOKUP(A13, Platform_DB!$B$1:$Z$1, Platform_DB!$B$5:$Z$5) -> 0.7 | K13: =1-ABS(B13-J13) -> 0.7 | L13: =_xlfn.XLOOKUP(A13, Platform_DB!$B$1:$Z$1, Platform_DB!$B$6:$Z$6) -> 0.7 | M13: =1-ABS(B13-L13) -> 0.7 | N13: =_xlfn.XLOOKUP(A13, Platform_DB!$B$1:$Z$1, Platform_DB!$B$7:$Z$7) -> 0.7 | O13: =1-ABS(B13-N13) -> 0.7
... A22: Developer Ecosystem & Community | B22: =AVERAGEIF(User_Responses!$B$2:$B$66, A22, User_Responses!$G$2:$G$66) -> 0.75 | C22: =SUMIF(User_Responses!$B$2:$B$66, A22, User_Responses!$H$2:$H$66) / SUM(User_Responses!H$2:$H$66) -> 0.034285714 | D22: =_xlfn.XLOOKUP(A22, Platform_DB!$B$1:$Z$1, Platform_DB!$B$2:$Z$2) -> 1 | E22: =1-ABS(B22-D22) -> 0.75 | F22: =_xlfn.XLOOKUP(A22, Platform_DB!$B$1:$Z$1, Platform_DB!$B$3:$Z$3) -> 0.9 | G22: =1-ABS(B22-F22) -> 0.85 | H22: =_xlfn.XLOOKUP(A22, Platform_DB!$B$1:$Z$1, Platform_DB!$B$4:$Z$4) -> 0.8 | I22: =1-ABS(B22-H22) -> 0.95 | J22: =_xlfn.XLOOKUP(A22, Platform_DB!$B$1:$Z$1, Platform_DB!$B$5:$Z$5) -> 0.6 | K22: =1-ABS(B22-J22) -> 0.85 | L22: =_xlfn.XLOOKUP(A22, Platform_DB!$B$1:$Z$1, Platform_DB!$B$6:$Z$6) -> 0.6 | M22: =1-ABS(B22-L22) -> 0.85 | N22: =_xlfn.XLOOKUP(A22, Platform_DB!$B$1:$Z$1, Platform_DB!$B$7:$Z$7) -> 0.6 | O22: =1-ABS(B22-N22) -> 0.85
D24: AWS | E24: Azure | F24: GCP | G24: OCI | H24: IBM | I24: Alibaba
C25: Vendor Scores | D25: =SUMPRODUCT($C$2:$C$21, E2:E21) -> 0.59628571 | E25: =SUMPRODUCT($C$2:$C$21, G2:G21) -> 0.59171429 | F25: =SUMPRODUCT($C$2:$C$21, I2:I21) -> 0.60238095 | G25: =SUMPRODUCT($C$2:$C$21, K2:K21) -> 0.64866667 | H25: =SUMPRODUCT($C$2:$C$21, M2:M21) -> 0.67533333 | I25: =SUMPRODUCT($C$2:$C$21, O2:O21) -> 0.70447619
A58: © 2026 Amit Kulkarni. All rights reserved.
