Workbook

Sheet User_Responses
A1: Category | B1: Client-Specific Question | C1: User Priority | D1: User Score
A2: SWIFT Environment Protection | B2: How securely segregated is the SWIFT secure zone from the general enterprise Active Directory infrastructure? A) The SWIFT zone uses a completely isolated, single-purpose AD forest with zero trust trusts to enterprise AD. B) SWIFT systems reside in a dedicated child domain, but share a forest root with general enterprise IT. C) Systems are segregated using AD groups and OU permissions within the primary enterprise domain controller. D) SWIFT systems share the same enterprise Active Directory infrastructure and admin accounts with no logical segregation . | C2: A | D2: {=_xlfn.SWITCH(C2,"A", 0.25,"B", 0.5, "C", 0.75,"D", 1)} -> 0.25
A3: SWIFT Environment Protection | B3: What level of strictness is applied to firewall rule configurations gating lateral access to local SWIFT infrastructure? A) Firewall rules enforce strict micro-segmentation, whitelisting only explicitly verified IP/port pairs with real-time anomaly. B) Rules are restricted to required business flows, but use broad subnet ranges rather than granular endpoint definitions. C) Basic firewall filtering is active, but rules are rarely reviewed and contain legacy or overly permissive definitions. D) Firewall rules allow broad inbound/outbound connections from general corporate networks into the SWIFT perimeter. | C3: A | D3: {=_xlfn.SWITCH(C3,"A", 0.25,"B", 0.5, "C", 0.75,"D", 1)} -> 0.25
A4: SWIFT Environment Protection | B4: How effectively are supporting infrastructure components (e.g., patching, scanning servers) isolated from the SWIFT zone? A) Patching and scanning servers are deployed natively inside the secure zone and cannot communicate with external assets. B) Shared corporate infrastructure is used but restricted via multi-factor jump hosts and specialized access lists. C) Infrastructure servers reside in general IT but have unrestricted administrative credentials to access SWIFT nodes. D) General IT management tools (SCCM, WSUS, vulnerability scanners) push updates to SWIFT zone without structural boundaries | C4: B | D4: {=_xlfn.SWITCH(C4,"A", 0.25,"B", 0.5, "C", 0.75,"D", 1)} -> 0.5
A5: SWIFT Environment Protection | B5: To what extent are internal data exfiltration risks managed via technical blocks on removable media? A) Removable media drives are strictly disabled at the OS/kernel level across all zone endpoints via centralized policy. B) Mass storage is blocked by default, but exceptions are manually provisioned for temporary administration needs. C) Use of USB or external storage relies purely on an unmonitored corporate policy without technical enforcement. D) Removable media drives are completely unblocked, allowing files and configurations to be copied freely. | C5: B | D5: {=_xlfn.SWITCH(C5,"A", 0.25,"B", 0.5, "C", 0.75,"D", 1)} -> 0.5
A6: SWIFT Environment Protection | B6: How robust are the credential-harvesting defenses guarding VPN pathways utilized by finance staff? A) VPN paths mandate phishing-resistant hardware keys combined with rigorous device health-attestation checks. B) MFA is enforced via standard mobile app push notifications, but device posture verification is missing. C) Ingress paths rely on SMS OTP or easily phishable software tokens without contextual access policies. D) Access paths rely entirely on static usernames and passwords without secondary verification factors. | C6: B | D6: {=_xlfn.SWITCH(C6,"A", 0.25,"B", 0.5, "C", 0.75,"D", 1)} -> 0.5
A7: Operating System Privileged Account Control | B7: Are root/administrator system logs protected against unauthorized, untraceable deletion or manipulation by privileged users? A) Root and administrator logs are streamed out in real-time to a WORM (Write-Once-Read-Many) centralized SIEM. B) Audit logs are sent to a central logging server daily, but local log file modification permissions remain unhardened. C) System events are collected locally on the system, making them vulnerable to deletion by a malicious admin. D) Privileged activities are completely untraceable, and system actions cannot be tied back to a specific individual. | C7: A | D7: {=_xlfn.SWITCH(C7,"A", 0.25,"B", 0.5, "C", 0.75,"D", 1)} -> 0.25
A8: Operating System Privileged Account Control | B8: How effectively is kernel vulnerability patch timing managed to prevent local privilege escalation on SWIFT nodes? A) Exploit mitigation tools are active, and kernel vulnerabilities are patched within 72 hours of public vendor release. B) Patches are deployed monthly, but the system lacks proactive runtime checks to block privilege escalation. C) Kernel patches are delayed by over 6 months due to legacy software compatibility or lack of testing cycles. D) Operating systems run highly legacy kernel versions with known unpatched root-execution vulnerabilities | C8: A | D8: {=_xlfn.SWITCH(C8,"A", 0.25,"B", 0.5, "C", 0.75,"D", 1)} -> 0.25
A9: Operating System Privileged Account Control | B9: What controls restrict the use of administrative utilities (e.g., PowerShell, Bash) to run unmonitored custom scripts? A) Utilities like PowerShell and Bash are locked down using constrained language modes and application whitelisting. B) Execution policies are active, but administrators can bypass them to run unapproved scripts. C) Tools are monitored by standard EDR, but any privileged account can execute arbitrary unvetted scripts natively. D) Administrative shells are completely unmonitored and can execute any malicious script or tool | C9: A | D9: {=_xlfn.SWITCH(C9,"A", 0.25,"B", 0.5, "C", 0.75,"D", 1)} -> 0.25
A10: Operating System Privileged Account Control | B10: How robust are your technical restrictions preventing memory dumping and credential extraction from administrator workstations? A) LSASS protection, Credential Guard, and secure boot mechanics are strictly enforced to block memory scraping tools. B) Standard endpoint security is deployed, but advanced OS-level memory isolation features remain disabled. C) Local password hashes are cached indefinitely in cleartext or weak formats on administrative workstations. D) Mimikatz or similar credential dumping utilities can run unimpeded to extract cached domain passwords. | C10: B | D10: {=_xlfn.SWITCH(C10,"A", 0.25,"B", 0.5, "C", 0.75,"D", 1)} -> 0.5
A11: Operating System Privileged Account Control | B11: Are default OS administrator accounts systematically disabled or renamed across all active endpoints? A) Default built-in OS administrative accounts are programmatically disabled, renamed, and managed via a LAPS framework. B) Accounts are renamed manually, but passwords remain static across multiple nodes in the cluster. C) Default accounts are left active, though they use complex strings that are rarely changed or updated. D) Default accounts (root, administrator) use well-known out-of-the-box passwords and are left fully active. | C11: C | D11: {=_xlfn.SWITCH(C11,"A", 0.25,"B", 0.5, "C", 0.75,"D", 1)} -> 0.75
A12: Virtualization or Cloud Platform Protection | B12: What mechanisms protect hypervisor or cloud orchestrator API layers from unauthorized configuration or security group manipulation? A) Access to management APIs requires dedicated multi-factor authentication coupled with rigorous IP whitelisting rules. B) Orchestration consoles are restricted to an administrative network but do not mandate strong phishing-resistant MFA. C) Cloud consoles are accessible directly over the internet using static user profiles with no network perimeter controls. D) API endpoints are unmonitored and accessible via shared, static credentials with no orchestration layer filtering. | C12: B | D12: {=_xlfn.SWITCH(C12,"A", 0.25,"B", 0.5, "C", 0.75,"D", 1)} -> 0.5
A13: Virtualization or Cloud Platform Protection | B13: What mechanisms protect hypervisor or cloud orchestrator API layers from unauthorized configuration or security group manipulation? A) Backup instances are encrypted locally with customer-managed keys, and access configurations are validated by automated code scripts. B) Backups are encrypted by default, but access permissions are audited manually on a periodic timeline. C) VM snapshots are stored in shared buckets without explicit IAM boundary lockdowns or lifecycle alerts. D) Storage instances are open to broad public directories, permitting unauthenticated download of SWIFT system disk images. | C13: B | D13: {=_xlfn.SWITCH(C13,"A", 0.25,"B", 0.5, "C", 0.75,"D", 1)} -> 0.5
... A78: Identity, Access, and Hygiene | B78: How comprehensive is the background screening protocol for contractors and staff entering sensitive roles? A) Background screening protocols check credit histories, criminal records, and cyber compliance metrics annually. B) Personnel undergo background checks during initial hiring, but skip follow-up screenings when changing roles. C) Screening steps evaluate permanent staff only, skipping verification checks for third-party contractors. D) 1.00: Onboarding skips background checks entirely, allowing unvetted profiles to enter sensitive positions | C78: C | D78: {=_xlfn.SWITCH(C78,"A", 0.25,"B", 0.5, "C", 0.75,"D", 1)} -> 0.75
A80: © 2026 Amit Kulkarni. All rights reserved.

Sheet Results
A1: Category | B1: Category Score Formula | C1: Weight Multipliers | D1: Weighted Scores
A2: SWIFT Environment Protection | B2: =AVERAGEIF(User_Responses!$A$2:$A$78, A2, User_Responses!$D$2:$D$78) -> 0.4 | C2: 2 | D2: =B2*C2 -> 0.8
A3: Operating System Privileged Account Control | B3: =AVERAGEIF(User_Responses!$A$2:$A$78, A3, User_Responses!$D$2:$D$78) -> 0.4 | C3: 3 | D3: =B3*C3 -> 1.2
A4: Virtualization or Cloud Platform Protection | B4: =AVERAGEIF(User_Responses!$A$2:$A$78, A4, User_Responses!$D$2:$D$78) -> 0.45 | C4: 1 | D4: =B4*C4 -> 0.45
A5: Restriction of Internet Access | B5: =AVERAGEIF(User_Responses!$A$2:$A$78, A5, User_Responses!$D$2:$D$78) -> 0.5 | C5: 3 | D5: =B5*C5 -> 1.5
A6: Internal Data Flow Security | B6: =AVERAGEIF(User_Responses!$A$2:$A$78, A6, User_Responses!$D$2:$D$78) -> 0.45 | C6: 2 | D6: =B6*C6 -> 0.9
A7: Security Updates | B7: =AVERAGEIF(User_Responses!$A$2:$A$78, A7, User_Responses!$D$2:$D$78) -> 0.70833333 | C7: 1 | D7: =B7*C7 -> 0.70833333
A8: Security Hardening | B8: =AVERAGEIF(User_Responses!$A$2:$A$78, A8, User_Responses!$D$2:$D$78) -> 0.65 | C8: 2 | D8: =B8*C8 -> 1.3
A9: Back Office Data Flow Security | B9: =AVERAGEIF(User_Responses!$A$2:$A$78, A9, User_Responses!$D$2:$D$78) -> 0.6 | C9: 3 | D9: =B9*C9 -> 1.8
A10: External Transmission Data Protection | B10: =AVERAGEIF(User_Responses!$A$2:$A$78, A10, User_Responses!$D$2:$D$78) -> 0.6 | C10: 3 | D10: =B10*C10 -> 1.8
A11: Operator Session Confidentiality and Integrity | B11: =AVERAGEIF(User_Responses!$A$2:$A$78, A11, User_Responses!$D$2:$D$78) -> 0.8 | C11: 2 | D11: =B11*C11 -> 1.6
A12: Vulnerability Scanning | B12: =AVERAGEIF(User_Responses!$A$2:$A$78, A12, User_Responses!$D$2:$D$78) -> 0.55 | C12: 1 | D12: =B12*C12 -> 0.55
A13: Critical Activity Outsourcing | B13: =AVERAGEIF(User_Responses!$A$2:$A$78, A13, User_Responses!$D$2:$D$78) -> 0.6 | C13: 3 | D13: =B13*C13 -> 1.8
... A16: Identity, Access, and Hygiene | B16: =AVERAGEIF(User_Responses!$A$2:$A$78, A16, User_Responses!$D$2:$D$78) -> 0.54166667 | C16: 3 | D16: =B16*C16 -> 1.625
B19: Global Weighted Score | C19: =SUM(D2:D16)/SUM(C2:C16) -> 0.57676768
B21: Threat Posture End State | C21: =IF(C19<=40%, "🟢 Optimized Security Posture", IF(C19<=60%, "🟡 Resilient Security Posture", IF(C19<=80%, "🟠 Elevated Exposure Posture", "🔴 Critical Threat Posture"))) -> 🟡 Resilient Security Posture
B25: Row Labels | C25: Sum of Weighted Scores | D25: Sum of Weight Multipliers
B26: Restriction of Internet Access | C26: 2.4 | D26: 3
B27: Identity, Access, and Hygiene | C27: 1.875 | D27: 3
B28: Critical Activity Outsourcing | C28: 1.8 | D28: 3
B29: External Transmission Data Protection | C29: 1.8 | D29: 3
B30: Back Office Data Flow Security | C30: 1.8 | D30: 3
B31: Operating System Privileged Account Control | C31: 1.65 | D31: 3
B32: Transaction Business Controls | C32: 1.6 | D32: 2
B33: Operator Session Confidentiality and Integrity | C33: 1.6 | D33: 2
B34: SWIFT Environment Protection | C34: 1.4 | D34: 2
B35: RMA (Relationship Management Application) Business Controls | C35: 1.4 | D35: 2
B36: Security Hardening | C36: 1.3 | D36: 2
B37: Internal Data Flow Security | C37: 0.9 | D37: 2
... B41: Grand Total | C41: 21.483333 | D41: 33
A44: © 2026 Amit Kulkarni. All rights reserved.

Sheet Results Interpretation
A1: States | B1: Definitions | C1: Operational Impact
A2: 🛡️ State 1: Optimized Security Posture (Score: 0% – 35%) | B2: The organization exhibits a highly mature security architecture. Technical controls are automated, segmentation is pristine, and privileged activities are stringently managed | C2: Low threat exposure. Highly resilient against sophisticated, multi-stage cyber attacks and insider risks
A3: ⚠️ State 2: Resilient Security Posture (Score: 35.01% – 55%) | B3: Core defensive perimeters are functional, and critical business validations are in place. However, some gaps exist due to manual dependencies or minor tracking lapses in asset lifecycles | C3: Moderate threat exposure. Capable of deflecting general opportunistic vectors, but highly targeted campaigns could exploit human validation points
A4: 🚨 State 3: Elevated Exposure Posture (Score: 55.01% – 75%) | B4: Major control vulnerabilities are present. The environment lacks robust segmentation, identity management has clear gaps, and security operations are reactive. | C4: High threat exposure. A compromise in the general corporate network carries a high probability of successful lateral movement into the SWIFT perimeter.
A5: ☠️ State 4: Critical Threat Posture (Score: 75.01% – 100%) | B5: Widespread failure or complete absence of standard security baselines. Credential hygiene is absent, access groups are unmonitored, and third-party interactions introduce severe risk | C5: Catastrophic exposure. The organization is exceptionally vulnerable to imminent fraud, ransomware distribution, or extensive long-term data exfiltration
A7: © 2026 Amit Kulkarni. All rights reserved.
