Workbook

Sheet Inputs
A1: Perspective | B1: Description | C1: Question | D1: User Response | E1: Numeric Score | F1: Capability Immediate Action
A2: Business Perspective: | B2: (Business case development) Evaluates the alignment of cloud investments with your broader business strategy and digital transformation goals | C2: How effectively does your organization build and validate financial and strategic business cases for cloud initiatives ? A) Ad-Hoc: We do not build formal business cases for the cloud; migrations are treated as mandatory IT upkeep or approved on a project-by-project basis without clear financial forecasting. B) Basic TCO: We build simple Total Cost of Ownership (TCO) assessments that compare basic on-premises hardware costs to estimated cloud infrastructure spend. C) Business-Aligned: We create comprehensive business cases that include both TCO and quantified business value metrics, such as accelerated time-to-market, improved developer productivity, and risk reduction. D) Continuously Optimized: Our business cases are dynamic, living documents; we continuously feed post-migration reality data back into our financial models to refine future cloud investment strategies. | D2: D | E2: {=_xlfn.IFS(D2="A", 1, D2="B", 2, D2="C", 3, D2="D", 4, TRUE, 0)} -> 4 | F2: {=_xlfn.IFS(E2=1, "IMMEDIATE ROADBLOCK: Remediate or hire external experts", E2=2, "TACTICAL GAP: Develop missing training/documentation", E2=3, "COMPETENCY SECURE: Operationalized and scaling cleanly", E2=4, "BEST IN CLASS: Automate further and share enterprise-wide", TRUE, "")} -> BEST IN CLASS: Automate further and share enterprise-wide
A3: Business Perspective: | B3: (Strategy Management) Evaluates the alignment of cloud investments with your broader business strategy and digital transformation goals | C3: Is your cloud roadmap explicitly mapped to your company's long-term commercial goals? A) No Alignment: Cloud decisions are made purely by IT to solve immediate infrastructure capacity issues, with zero alignment to corporate business strategies. B) Reactive Scaling: Our cloud initiatives generally support ongoing business projects, but we lack a unified roadmap connecting cloud investments directly to long-term commercial goals. C) Strategic Roadmap: We maintain a formal cloud strategy roadmap that explicitly details how cloud technologies will enable specific business targets over the next 18–36 months. D) Business Driver: The cloud strategy is identical to our corporate strategy; all business transformations, market entries, and expansions are designed with cloud capabilities as the foundation. | D3: D | E3: {=_xlfn.IFS(D3="A", 1, D3="B", 2, D3="C", 3, D3="D", 4, TRUE, 0)} -> 4 | F3: {=_xlfn.IFS(E3=1, "IMMEDIATE ROADBLOCK: Remediate or hire external experts", E3=2, "TACTICAL GAP: Develop missing training/documentation", E3=3, "COMPETENCY SECURE: Operationalized and scaling cleanly", E3=4, "BEST IN CLASS: Automate further and share enterprise-wide", TRUE, "")} -> BEST IN CLASS: Automate further and share enterprise-wide
A4: Business Perspective: | B4: (Portfolio Management) Evaluates the alignment of cloud investments with your broader business strategy and digital transformation goals | C4: How well are your applications categorized and prioritized for migration or modernization based on business value ? A) Fragmented Inventory: We lack a centralized inventory of business applications; cloud migration candidates are chosen based on urgency or arbitrary team preferences. B) Basic Classification: We maintain a basic application registry, but candidates are evaluated purely by technical fit rather than business criticality or financial return. C) Structured Modernization: Applications are categorized using a formal "6 Rs" framework (Rehost, Replatform, Refactor, etc.), balancing technical complexity against commercial urgency. D) Dynamic Lifecycle: Application portfolios are continuously managed via an automated governance pipeline that tracks business value, cost, and health to deprecate or modernize software dynamically. | D4: D | E4: {=_xlfn.IFS(D4="A", 1, D4="B", 2, D4="C", 3, D4="D", 4, TRUE, 0)} -> 4 | F4: {=_xlfn.IFS(E4=1, "IMMEDIATE ROADBLOCK: Remediate or hire external experts", E4=2, "TACTICAL GAP: Develop missing training/documentation", E4=3, "COMPETENCY SECURE: Operationalized and scaling cleanly", E4=4, "BEST IN CLASS: Automate further and share enterprise-wide", TRUE, "")} -> BEST IN CLASS: Automate further and share enterprise-wide
A5: Business Perspective: | B5: (Innovation Management) Evaluates the alignment of cloud investments with your broader business strategy and digital transformation goals | C5: Do you have formal mechanisms to use cloud services to rapidly build, test, and launch new products ? A) Inhibited: Strict procurement timelines, legacy infrastructure setups, and a fear of failure make testing new ideas or prototyping new products incredibly slow and expensive. B) Ad-Hoc Sandboxes: Developers occasionally use basic cloud accounts to build isolated proofs of concept, but moving successful ideas to production takes months of manual approvals. C) Structured Pipeline: We leverage cloud-native features (serverless, low-code, marketplace tools) within isolated sandboxes to rapidly prototype, validate, and move ideas to production in weeks. D) Continuous Disruption: Innovation is fully operationalized; automated product-testing frameworks allow teams to safely run live A/B tests and pivot or kill features instantly based on real-time customer data. | D5: D | E5: {=_xlfn.IFS(D5="A", 1, D5="B", 2, D5="C", 3, D5="D", 4, TRUE, 0)} -> 4 | F5: {=_xlfn.IFS(E5=1, "IMMEDIATE ROADBLOCK: Remediate or hire external experts", E5=2, "TACTICAL GAP: Develop missing training/documentation", E5=3, "COMPETENCY SECURE: Operationalized and scaling cleanly", E5=4, "BEST IN CLASS: Automate further and share enterprise-wide", TRUE, "")} -> BEST IN CLASS: Automate further and share enterprise-wide
A6: Business Perspective: | B6: (Product Management) Evaluates the alignment of cloud investments with your broader business strategy and digital transformation goals | C6: Are your IT services managed as value-driven business products rather than cost-center projects ? A) Project-Centric: IT operates strictly under a temporary "project" model with fixed budgets and end dates; teams hand off applications to a separate support group and disperse. D) Hybrid Delivery: Some modern apps use cross-functional teams, but funding models and performance metrics are still anchored to traditional, fixed-scope IT project delivery. C) Product-Driven: Applications are managed as continuous business products with dedicated funding, persistent cross-functional teams, and success measured by long-term user adoption and business value. D) Platform-as-a-Product: Internal infrastructure, data, and security systems are treated as self-service digital products, complete with internal SLAs and continuous feedback loops. | D6: D | E6: {=_xlfn.IFS(D6="A", 1, D6="B", 2, D6="C", 3, D6="D", 4, TRUE, 0)} -> 4 | F6: {=_xlfn.IFS(E6=1, "IMMEDIATE ROADBLOCK: Remediate or hire external experts", E6=2, "TACTICAL GAP: Develop missing training/documentation", E6=3, "COMPETENCY SECURE: Operationalized and scaling cleanly", E6=4, "BEST IN CLASS: Automate further and share enterprise-wide", TRUE, "")} -> BEST IN CLASS: Automate further and share enterprise-wide
A7: Business Perspective: | B7: Strategic PartnerShip) Evaluates the alignment of cloud investments with your broader business strategy and digital transformation goals | C7: How well-integrated are your cloud vendors and system integrators into your long-term business strategy ? A) Transactional: Vendors and Cloud Service Providers (CSPs) are treated strictly as utility providers; communication is limited to resolving service outages or billing disputes. B) Preferred Suppliers: We have preferred cloud partners, but engagements are scoped entirely on an ad-hoc project basis without long-term shared incentives. C) Collaborative Ecosystem: We maintain strategic multi-year relationships with CSPs and global system integrators to secure co-investment funds, training credits, and deep technical support. D) Joint Innovation: We co-develop intellectual property or launch joint go-to-market initiatives with our cloud partners, integrating our business roadmaps with their feature release plans. | D7: D | E7: {=_xlfn.IFS(D7="A", 1, D7="B", 2, D7="C", 3, D7="D", 4, TRUE, 0)} -> 4 | F7: {=_xlfn.IFS(E7=1, "IMMEDIATE ROADBLOCK: Remediate or hire external experts", E7=2, "TACTICAL GAP: Develop missing training/documentation", E7=3, "COMPETENCY SECURE: Operationalized and scaling cleanly", E7=4, "BEST IN CLASS: Automate further and share enterprise-wide", TRUE, "")} -> BEST IN CLASS: Automate further and share enterprise-wide
A8: Business Perspective: | B8: (Data Monetization) Evaluates the alignment of cloud investments with your broader business strategy and digital transformation goals | C8: Does your organization actively leverage cloud analytics to generate new revenue streams or business models ? A) Untapped: Data is locked away in operational silos or legacy systems; it is rarely organized well enough to support basic decision-making, let alone generate business value. B) Descriptive Reporting: We use basic cloud data warehouses to generate internal retroactive reports and static dashboards for business leaders. C) Data Products: We actively clean, aggregate, and package cloud data to optimize operations, predict customer behavior, or deliver commercial data services to external clients. D) AI-Driven Ecosystem: Advanced machine learning models and automated data pipelines dynamically alter pricing, product recommendations, or market strategies in real time to generate automated revenue. | D8: D | E8: {=_xlfn.IFS(D8="A", 1, D8="B", 2, D8="C", 3, D8="D", 4, TRUE, 0)} -> 4 | F8: {=_xlfn.IFS(E8=1, "IMMEDIATE ROADBLOCK: Remediate or hire external experts", E8=2, "TACTICAL GAP: Develop missing training/documentation", E8=3, "COMPETENCY SECURE: Operationalized and scaling cleanly", E8=4, "BEST IN CLASS: Automate further and share enterprise-wide", TRUE, "")} -> BEST IN CLASS: Automate further and share enterprise-wide
A9: Business Perspective: | B9: (Benefits Realization) Evaluates the alignment of cloud investments with your broader business strategy and digital transformation goals | C9: Do you consistently measure the post-migration business value against your original business case ? A) Unmeasured: Once a cloud project or migration is completed, we do not track whether it achieved its original financial or operational business objectives. B) Anecdotal Evidence: We track high-level IT changes (e.g., hardware decommissioning), but we lack empirical metrics proving that the cloud improved business speed or revenue. C) Closed-Loop Tracking: We systematically audit post-migration applications against baseline financial and performance metrics established in the initial business case. D) Automated Value Dashboards: Business value parameters (e.g., engineering velocity gains, infrastructure savings, uptime value) are aggregated into executive dashboards to guide capital allocation. | D9: D | E9: {=_xlfn.IFS(D9="A", 1, D9="B", 2, D9="C", 3, D9="D", 4, TRUE, 0)} -> 4 | F9: {=_xlfn.IFS(E9=1, "IMMEDIATE ROADBLOCK: Remediate or hire external experts", E9=2, "TACTICAL GAP: Develop missing training/documentation", E9=3, "COMPETENCY SECURE: Operationalized and scaling cleanly", E9=4, "BEST IN CLASS: Automate further and share enterprise-wide", TRUE, "")} -> BEST IN CLASS: Automate further and share enterprise-wide
A10: Human Perspective: | B10: (Culture Evolution) Focuses on organizational evolution, culture, change management, and building a cloud-ready workforce | C10: How actively does your organization foster a culture of experimentation, psychological safety, and continuous learning? A) Risk-Averse & Siloed: Blame is placed when deployments go wrong; teams work in tight silos, rigidly follow legacy checklists, and actively resist new ways of working. B) Localized Agility: A few application development teams embrace cloud culture, but the broader enterprise remains deeply bureaucratic and resistant to change. C) Psychological Safety: Failure is explicitly decoupled from blame; blameless post-mortems are standard practice, and experimentation is actively rewarded across teams. D) Continuous Learning Org: Experimentation is woven into the organizational DNA; teams share failure lessons across business boundaries, and self-disruption is seen as a core strength. | D10: D | E10: {=_xlfn.IFS(D10="A", 1, D10="B", 2, D10="C", 3, D10="D", 4, TRUE, 0)} -> 4 | F10: {=_xlfn.IFS(E10=1, "IMMEDIATE ROADBLOCK: Remediate or hire external experts", E10=2, "TACTICAL GAP: Develop missing training/documentation", E10=3, "COMPETENCY SECURE: Operationalized and scaling cleanly", E10=4, "BEST IN CLASS: Automate further and share enterprise-wide", TRUE, "")} -> BEST IN CLASS: Automate further and share enterprise-wide
A11: Human Perspective: | B11: (Organizational Structure) Focuses on organizational evolution, culture, change management, and building a cloud-ready workforce | C11: Do you have a functional, cross-functional Cloud Center of Excellence (CCoE) leading your adoption? A) Isolated Silos: Our traditional IT infrastructure, networking, and application teams operate independently, passing tickets back and forth to deploy cloud resources. B) Virtual Cloud Team: We have a loose, informal group of cloud enthusiasts from different teams who meet occasionally to discuss standards, but they have no formal mandate or authority. C) Dedicated CCoE: We have a fully staffed, cross-functional Cloud Center of Excellence (CCoE) that actively publishes landing zone patterns, sets guardrails, and accelerates onboarding across the enterprise. D) Decentralized & Federated: The CCoE acts purely as a platform governance body; individual business units are completely autonomous and self-sufficient in deploying their own cloud resources safely. | D11: D | E11: {=_xlfn.IFS(D11="A", 1, D11="B", 2, D11="C", 3, D11="D", 4, TRUE, 0)} -> 4 | F11: {=_xlfn.IFS(E11=1, "IMMEDIATE ROADBLOCK: Remediate or hire external experts", E11=2, "TACTICAL GAP: Develop missing training/documentation", E11=3, "COMPETENCY SECURE: Operationalized and scaling cleanly", E11=4, "BEST IN CLASS: Automate further and share enterprise-wide", TRUE, "")} -> BEST IN CLASS: Automate further and share enterprise-wide
A12: Human Perspective: | B12: (Leadership Capability) Focuses on organizational evolution, culture, change management, and building a cloud-ready workforce | C12: Are your executive sponsors actively trained and visibly leading the cloud transformation journey? A) Disengaged: Senior executives view the cloud purely as a technical IT infrastructure replacement and provide no active sponsorship or guidance for operational changes. B) Passive Approval: Executives support cloud adoption conceptually and fund the projects, but they lack a deep understanding of the organizational shifts required to succeed. C) Active Advocates: Executive leaders are trained in cloud business fundamentals, visible in steering committee meetings, and actively break down political silos across the business. D) Transformational Visionaries: Leadership champions cloud adoption as a core business differentiator, aligning executive compensation and organizational KPIs to modern digital metrics. | D12: D | E12: {=_xlfn.IFS(D12="A", 1, D12="B", 2, D12="C", 3, D12="D", 4, TRUE, 0)} -> 4 | F12: {=_xlfn.IFS(E12=1, "IMMEDIATE ROADBLOCK: Remediate or hire external experts", E12=2, "TACTICAL GAP: Develop missing training/documentation", E12=3, "COMPETENCY SECURE: Operationalized and scaling cleanly", E12=4, "BEST IN CLASS: Automate further and share enterprise-wide", TRUE, "")} -> BEST IN CLASS: Automate further and share enterprise-wide
A13: Human Perspective: | B13: (Workforce Transformation) Focuses on organizational evolution, culture, change management, and building a cloud-ready workforce | C13: Is there a structured plan to transition legacy IT staff into modern cloud-native roles? A) No Transition Plan: Legacy IT workers (sysadmins, database administrators) are expected to absorb cloud roles naturally without formal training plans or job description updates. B) Ad-Hoc Upskilling: We offer occasional classroom training or provide access to online courses, but workers are left to find time for learning around their daily legacy tasks. C) Structured Career Pathways: We maintain explicit, funded career development pathways mapping legacy roles directly to modern cloud roles (e.g., SysAdmin to DevOps Engineer). D) Self-Sustaining Talent Guilds: Continuous skill evolution is fully integrated into HR systems; internal technical guilds mentor peers, and workforce rotation guarantees persistent upskilling. | D13: D | E13: {=_xlfn.IFS(D13="A", 1, D13="B", 2, D13="C", 3, D13="D", 4, TRUE, 0)} -> 4 | F13: {=_xlfn.IFS(E13=1, "IMMEDIATE ROADBLOCK: Remediate or hire external experts", E13=2, "TACTICAL GAP: Develop missing training/documentation", E13=3, "COMPETENCY SECURE: Operationalized and scaling cleanly", E13=4, "BEST IN CLASS: Automate further and share enterprise-wide", TRUE, "")} -> BEST IN CLASS: Automate further and share enterprise-wide
... A48: Operations Perspective: | B48: (Capacity Planning) Measures your day-to-day management, observability, and service reliability in a cloud environment. | C48: Does your team use automated demand forecasting rather than buying fixed, upfront infrastructure headroom? A) Guesswork Allocation: We provision cloud capacity based on historical on-premises hardware volumes, resulting in massive over-provisioning and wasted budget. B) Periodic Manual Reviews: Engineers look at cloud capacity dashboards once a quarter to adjust server sizes manually based on past peak workloads. C) Automated Dynamic Scaling: Infrastructure capacity expands and contracts automatically based on real-time application load metrics, matching capacity to actual customer demand. D) Algorithmic Demand Forecasting: Advanced predictive algorithms analyze market cycles, business expansion patterns, and seasonal trends to purchase optimal cloud capacity reservations automatically. | D48: D | E48: {=_xlfn.IFS(D48="A", 1, D48="B", 2, D48="C", 3, D48="D", 4, TRUE, 0)} -> 4 | F48: {=_xlfn.IFS(E48=1, "IMMEDIATE ROADBLOCK: Remediate or hire external experts", E48=2, "TACTICAL GAP: Develop missing training/documentation", E48=3, "COMPETENCY SECURE: Operationalized and scaling cleanly", E48=4, "BEST IN CLASS: Automate further and share enterprise-wide", TRUE, "")} -> BEST IN CLASS: Automate further and share enterprise-wide
A50: © 2026 Amit Kulkarni All rights reserved

Sheet Dashboards
A1: CAF Domain Perspective | B1: Average Score | C1: Result
A2: Business Perspective: | B2: =AVERAGEIF(Inputs!A:A, A2, Inputs!E:E) -> 4
A3: Human Perspective: | B3: =AVERAGEIF(Inputs!A:A, A3, Inputs!E:E) -> 4
A4: Governance Perspective: | B4: =AVERAGEIF(Inputs!A:A, A4, Inputs!E:E) -> 4
A5: Platform Perspective: | B5: =AVERAGEIF(Inputs!A:A, A5, Inputs!E:E) -> 4
A6: Security Perspective: | B6: =AVERAGEIF(Inputs!A:A, A6, Inputs!E:E) -> 4
A7: Operations Perspective: | B7: =AVERAGEIF(Inputs!A:A, A7, Inputs!E:E) -> 4
C8: Target Cloud Operating Model & Execution Strategy
C9: {=_xlfn.IFS( Inputs!E35 = 1, "STATE 1 - SYSTEM RETIREMENT PHASE: Target workload is flagged as sunset/decommission mode. Halt all cloud migration planning to prevent stranded capital waste.", COUNTIF(Inputs!E2:E48, 1) > 15, "STATE 2 - CRITICAL CAPABILITY COLLAPSE: Extreme operational gaps (>15 zeros/ones). Total organizational transformation and external engineering injection required before infrastructure kickoff.", COUNTIF(Inputs!E2:E48, 1) > 8, "STATE 3 - RESTRUCTURE & REMEDIATE: Legacy Operating Model. Fragmented foundational skills. Establish a mandatory CCoE and build automated onboarding training pipelines immediately.", AVERAGEIF(Inputs!A2:A48, "Security Perspective:", Inputs!E2:E48) < 2, "STATE 4 - SECURITY LANDING ZONE BLOCK: High-risk isolation posture. Multi-tenant IAM, edge defenses, and data encryption metrics are deficient. Halt active migrations until core security guardrails are operationalized.", AVERAGEIF(Inputs!A2:A48, "Governance Perspective:", Inputs!E2:E48) < 2, "STATE 5 - FINOPS BUDGETARY ALERT: High financial bleed risk. Cloud billing transparency, project tagging controls, and allocation structures are reactive. Impose cost gates before environment scaling.", AND(AVERAGEIF(Inputs!A2:A48, "Platform Perspective:", Inputs!E2:E48) < 2, AVERAGEIF(Inputs!A2:E48, "Operations Perspective:", Inputs!E2:E48) < 2), "STATE 6 - TECHNICAL DEBT SATURATION: Combined Infrastructure & Operations deficit. App monitoring frameworks and provisioning engines are manual. Modernize deployment pipelines before code movements.", AVERAGEIF(Inputs!A2:A48, "Human Perspective:", Inputs!E2:E48) < 2, "STATE 7 - ORGANIZATIONAL RESISTANCE ANOMALY: Team/Culture friction block. High talent gap and missing change acceleration frameworks. Focus exclusively on upskilling and sponsor alignment workshops.", AVERAGEIF(Inputs!A2:A48, "Business Perspective:", Inputs!E2:E48) < 2, "STATE 8 - STRATEGIC ALIGNMENT DISCONNECT: Tech-driven silo trap. Cloud roadmaps are detached from commercial monetization goals and business case metrics. Re-align executive sponsorship budgets.", AND(AVERAGE(Inputs!E2:E48) >= 3.5, COUNTIF(Inputs!E2:E48, "<3") = 0), "STATE 9 - ULTRALIGHT COMPOSABLE MESH: Elite Multi-Cloud Fabric (Maturity >= 3.5 with zero items below Level 3). Optimized for autonomous edge pipelines and real-time distributed data networks.", AVERAGE(Inputs!E2:E48) >= 3.5, "STATE 10 - FEDERATED DECENTRALIZED PLATFORM: Modern Digital Enterprise. High baseline capability. Product teams can safely auto-provision resources natively using automated Policy-as-Code guardrails.", AVERAGE(Inputs!E2:E48) >= 3, "STATE 11 - ACCELERATED CENTRAL CCoE: Scaled Cloud Practice. Core landing zones, foundational blue-printing, and cross-functional expert guilds are successfully accelerating standard workload onboarding.", AVERAGE(Inputs!E2:E48) >= 2.5, "STATE 12 - OPERATIONAL CORE ESTABLISHED: Standard Adoption. Shared platform templates and central security configurations are stable. Strategy needs to pivot from migration toward active cost optimization.", AVERAGE(Inputs!E2:E48) >= 2, "STATE 13 - SILOED TACTICAL PROTOTYPING: Fragmented Project Adoption. Cloud usage is restricted to ad-hoc business unit sandboxes. Focus on unifying corporate governance and centralizing architecture frameworks.", AVERAGE(Inputs!E2:E48) >= 1.5, "STATE 14 - CHAOTIC AD-HOC DEPLOYMENT: Initial reactive footprint. High frequency of manual infrastructure clicks, missing audit trails, and unpredictable billing. Freeze expansions for architectural assessment.", TRUE, "STATE 15 - INVALID MATURITY RANGE: Re-assess organizational ready state parameters. Verify all row calculations and dropdown inputs match framework mapping rules." )} -> STATE 9 - ULTRALIGHT COMPOSABLE MESH: Elite Multi-Cloud Fabric (Maturity >= 3.5 with zero items below Level 3). Optimized for autonomous edge pipelines and real-time distributed data networks.
A27: © 2026 Amit Kulkarni All rights reserved

Sheet Descriptions
A1: Critical Blockers & Risk Mitigation States (States 1 – 3) | B1: States
A2: STATE 1: System Retirement Phase Business Explanation: The workload or operational pattern being assessed is nearing the end of its corporate lifecycle and will be decommissioned within 12 months. Spending capital to migrate or modernize this system is a direct loss of budget. Actionable Next Steps: Freeze Budgets: Immediately halt all cloud architecture, design, and engineering hours allocated to this asset. Sweeping Review: Divert saved cloud credits to high-growth target systems. Document Legacy Knowledge: Archive essential logs and data patterns for historical tracking before the final shutdown. | B2: STATE 2: Critical Capability Collapse Business Explanation: The organization suffers from widespread structural deficits across all operational domains. Migrating to the cloud right now will guarantee catastrophic cost spikes, team burnout, and operational failure. Actionable Next Steps: Impose an Absolute Infrastructure Freeze: Do not spin up production resources. Inject External Experts: Subcontract specialized Managed Service Providers (MSPs) to build baseline platforms while your internal team upskills. Deploy Emergency Governance: Mandate a single, centralized procurement lock on all corporate cloud account creations.
A4: STATE 3: Restructure & Remediate (Legacy Operating Model) Business Explanation: The company is operating with an outdated, fragmented IT mindset. Teams are working in tight silos, utilizing manual infrastructure setups, and lacking unified cloud guidelines. Actionable Next Steps: Launch a Core CCoE: Authorize a dedicated cross-functional Cloud Center of Excellence (CCoE) with representatives from Security, Finance, Operations, and Architecture. Establish Cloud Onboarding Tracks: Design basic cloud literacy pathways across different departments. Centralize Landing Zone Design: Restrict individual teams from manual console access.
A6: Domain-Specific Deficit Alerts (States 4 – 8)
A7: STATE 4: Security Landing Zone Block Business Explanation: The technical team understands general cloud concepts, but the corporate cloud footprint lacks enterprise guardrails. Identity controls (IAM), perimeter protection, and automated encryption are missing or weak. Actionable Next Steps: Deploy Policy-as-Code Guardrails: Activate tools like AWS Control Tower or Azure Blueprints to enforce mandatory multi-factor authentication (MFA). Lock Down API Integrity: Run automated credential rotations and enforce end-to-end data encryption rules across all storage tiers. Enact Ingress/Egress Controls: Funnel all cloud traffic through centralized web application firewalls (WAF). | B7: STATE 5: FinOps Budgetary Alert Business Explanation: Cloud spending is reactive and unmonitored. The business is at high risk for unexpected, massive monthly cloud bill shocks due to untagged systems and orphan resources. Actionable Next Steps: Enforce a Tagging Standard: Build automated pipelines that reject the creation of any cloud resource that lacks owner or project cost tags. Configure Cloud Anomalies Detectors: Sync immediate alerts to communication channels (Slack/Teams) when cost spikes happen. Establish Monthly FinOps Cadences: Mandate a recurring financial alignment review between engineering leads and finance.
A9: STATE 6: Technical Debt Saturation Business Explanation: A dual infrastructure and operations deficit. Software development pipelines are manual and resource health tracking is blind, leading to extended downtime risks. Actionable Next Steps: Mandate Infrastructure as Code (IaC): Ban manual cloud console configurations; deploy all infrastructure using version-controlled templates (Terraform/Bicep). Deploy Unified Telemetry Hubs: Consolidate distributed infrastructure logs into a centralized dashboard (Datadog, AWS CloudWatch, or Azure Monitor). Automate CI/CD Checkpoints: Standardize build cycles with automated code quality validation. | B9: STATE 7: Organizational Resistance Anomaly Business Explanation: The technology is viable, but the human element is lagging. Corporate change acceleration, executive alignment, and training tracks are failing, causing silent team sabotage. Actionable Next Steps: Host Leadership Alignment Seminars: Secure visible, active sponsorship from senior executives. Launch a Cloud Champion Guild: Empower internal technical champions to run peer-to-peer mentoring lunch-and-learns. Address Job-Role Friction: Update outdated IT job descriptions to modern cloud engineering definitions to clear employee anxiety.
A11: STATE 8: Strategic Alignment Disconnect Business Explanation: The technical team is building cloud infrastructure in a silo, completely detached from the company’s commercial roadmap, product strategies, or financial metrics. Actionable Next Steps: Re-anchor the Business Case: Quantify migration targets based on strategic goals (like faster feature release speeds) rather than simple server cost comparisons. Embed Product Owners into IT Sprints: Assign business leads to participate directly in development design phases. Formulate Value Dashboards: Build executive reporting metrics connecting IT spend directly to business transaction gains.
A13: Maturity Optimization Tiers (States 9 – 14)
A14: STATE 9: Ultralight Composable Mesh Business Explanation: The absolute gold standard of enterprise agility. The organization runs an evenly distributed, secure multi-cloud footprint with zero operational dependencies or performance lags. Actionable Next Steps: Pioneer Advanced Architectures: Migrate legacy transactional logic toward distributed database meshes. Leverage Cross-Cloud Redundancy: Deploy global anycast routing networks to execute zero-downtime cross-region system failovers. Contribute to Open Source: Document internal platform wins to build a top-tier employer engineering brand. | B14: STATE 10: Federated Decentralized Platform Business Explanation: High corporate maturity. The central cloud team has successfully shifted from a gatekeeper model to an enablement platform. Product teams can safely scale software autonomously. Actionable Next Steps: Optimize Internal Developer Portals: Package pre-approved cloud architectures into simple, single-click developer service catalogs. Scale Unit Economics Analytics: Dynamically track real-time infrastructure cost metrics per single customer transaction. Refine Edge Automated Remediation: Authorize algorithms to self-heal platform drifts and clear security vulnerabilities automatically.
A16: STATE 11: Accelerated Central CCoE Business Explanation: The organization has a highly functional Cloud Center of Excellence driving adoption. Foundational multi-account architectures are stable, and teams are onboarding cleanly. Actionable Next Steps: Transition from Migration to Optimization: Pivot engineering goals away from rapid cloud onboarding and toward fine-tuning compute density. Establish Advanced Specialized Training: Transition the general IT workforce toward deep, advanced cloud specialty certifications (Data, AI, Security). Standardize Shared Services Mesh: Centralize corporate traffic controls to lower network transit costs. | B16: STATE 12: Operational Core Established Business Explanation: Standard baseline adoption. The enterprise has stable virtual machine configurations and basic security logging, but relies heavily on manual oversight to adjust capacity. Actionable Next Steps: Implement Automated Scaling Controls: Configure infrastructure parameters to expand and contract dynamically based on real-time traffic curves. Audit Database Layouts: Migrate high-maintenance databases onto fully managed, serverless database instances (AWS RDS or Azure SQL). Consolidate Commitments: Maximize cloud provider savings by locking in targeted, multi-year Compute Savings Plans.
A18: STATE 13: Siloed Tactical Prototyping Business Explanation: Cloud usage is fragmented. Individual business departments are testing or deploying software in independent cloud sandboxes without centralized security supervision or shared billing standards. Actionable Next Steps: Conduct a Discovery Pass: Identify and catalogue all shadow-IT cloud accounts across corporate credit cards. Enforce Central Organizational Parent Roots: Pull scattered accounts under a single master organization structure (AWS Organizations or Azure Management Groups). Draft a Master Baseline Landing Zone Blueprint: Enforce standard corporate firewall rules across all discovered zones. | B18: STATE 14: Chaotic Ad-Hoc Deployment Business Explanation: Initial reactive operational footprint. Cloud services are launched haphazardly via the console, lacking audit trails, secure perimeters, or budget allocations. Actionable Next Steps: Enact an Expansion Freeze: Immediately restrict the deployment of new production services. Run a Comprehensive Security Clean-Up: Eliminate public internet access configurations from databases and rotate standing administration access credentials. Deploy Basic Cost Alerts: Set hard threshold limits via cloud budget tools to prevent unexpected invoices.
A20: Operational Fallback State (State 15)
A21: STATE 15: Invalid Maturity Range Business Explanation: The survey data input is corrupt or inconsistent. The mathematical parameters evaluate to non-standard indices, rendering the strategy recommendation invalid. Actionable Next Steps: Audit Workbook Entries: Verify that all 40 capability fields in Column D contain exact A, B, C, or D entries. Fix Range References: Confirm that cell formulas on the Dashboard sheet are aligned to row boundaries. Re-initialize Sheet: Reset missing fields to a baseline option to restore the rules engine logic.
A23: © 2026 Amit Kulkarni All rights reserved
