Workbook

Sheet Inputs
A1: Category | B1: Client-Specific Question | C1: User Priority | D1: User Score
A2: Prompt Injection Defenses | B2: Direct Prompt Injection Filtering A) Dual-LLM guardrail systems inspect all user inputs using specific adversarial classification models before routing. B) Input text passes through standard regex structures and semantic vector checks, catching basic jailbreak strings. C) Filtering relies on basic system prompt instructions (e.g., "Do not bypass rules"), leaving inputs unvalidated. D) User inputs pass directly to the LLM context window without screening, exposing the model to jailbreaks. | C2: D | D2: {=_xlfn.SWITCH(C2,"A", 0.25,"B", 0.5, "C", 0.75,"D", 1)} -> 1
A3: Prompt Injection Defenses | B3: Indirect Prompt Injection Isolation A) External data (e.g., web pages, uploaded files) is treated as unvetted text and isolated from the main system context. B) Untrusted text passes through structural parsers, but shares the same system privilege tier as the user session. C) External data pulls merge directly into user prompt fields, relying entirely on the base model to ignore rogue instructions. D) The model fetches untrusted external data sources and processes them natively without safety controls | C3: D | D3: {=_xlfn.SWITCH(C3,"A", 0.25,"B", 0.5, "C", 0.75,"D", 1)} -> 1
A4: Prompt Injection Defenses | B4: System Prompt Confidentiality A) System prompts use dynamic context structures and token-level access blocks to prevent system prompt leakage. B) The prompt contains text warnings against disclosure, and outbound filters catch explicit leaking keywords. C) System instructions are static text properties within code, relying on the model's base alignment for safety. D) Prompts lack disclosure protection, allowing users to extract full system instructions with basic queries | C4: D | D4: {=_xlfn.SWITCH(C4,"A", 0.25,"B", 0.5, "C", 0.75,"D", 1)} -> 1
A5: Prompt Injection Defenses | B5: Context Window Memory Flushing A) Chat history sessions drop system-level prompt states automatically after exactly 5 minutes of inactivity. B) Context history sessions expire after 30 minutes, but cleartext cache properties remain active in volatile memory. C) Chat histories are stored indefinitely, allowing historical manipulation attempts to influence active sessions. D) Session history lacks timeout parameters, allowing long-running prompt tracking exploits to persist. | C5: D | D5: {=_xlfn.SWITCH(C5,"A", 0.25,"B", 0.5, "C", 0.75,"D", 1)} -> 1
A6: Prompt Injection Defenses | B6: Adversarial Token Disruption A) Tokenization layers actively block special system tokens (e.g., <|endoftext|>) to prevent structural bypasses. B) Security layers flag unusual token frequencies, but lack programmatic blocks to drop malformed structures. C) Tokens undergo standard baseline parsing without security reviews for specialized adversarial formatting. D) Token inputs pass directly to the neural engine, permitting structural bypass attacks via specialized token formats. | C6: D | D6: {=_xlfn.SWITCH(C6,"A", 0.25,"B", 0.5, "C", 0.75,"D", 1)} -> 1
A7: Insecure Output Handling | B7: Downstream Execution Escaping A) Privilege escalation uses automated Just-In-Time (JIT) workflows that clear all elevated permissions within 1 hour. B) Elevated access follows manual engineering request sign-offs, remaining active for a full business day. C) High-level permissions reside permanently on standard user profiles, relying on verbal policy to prevent abuse. D) Shared administrator keys are stored on unprotected systems with zero isolation parameters. | C7: D | D7: {=_xlfn.SWITCH(C7,"A", 0.25,"B", 0.5, "C", 0.75,"D", 1)} -> 1
A8: Insecure Output Handling | B8: Structured Output Type Constraints A) Applications enforce strict JSON schemas or Pydantic validation on all responses before processing down-stream. B) Code functions check response data types, but lack rigorous validation structures to catch malicious schema drift. C) Outputs are parsed via loose try-except loops, handling processing errors without checking response content values. D) Downstream code processes raw model strings directly, exposing internal infrastructure to injection attacks. | C8: D | D8: {=_xlfn.SWITCH(C8,"A", 0.25,"B", 0.5, "C", 0.75,"D", 1)} -> 1
A9: Insecure Output Handling | B9: Indirect Command Injection Defenses A) Model-generated code or commands run exclusively within short-lived, isolated serverless sandbox environments. B) Generated instructions run on standard environments, but require administrative tokens before execution. C) Instructions run with full user account privileges, relying entirely on code review processes to catch errors. D) LLM responses flow directly into system shells (e.g., eval()), allowing arbitrary remote code execution. | C9: D | D9: {=_xlfn.SWITCH(C9,"A", 0.25,"B", 0.5, "C", 0.75,"D", 1)} -> 1
A10: Insecure Output Handling | B10: Content Security Policy (CSP) Alignment A) Strict CSP definitions block data exfiltration by restricting model outputs from calling unapproved web domains. B) CSP parameters are active, but use broad whitelists that allow data transfers to generic cloud endpoints. C) Domain constraints use legacy parameters that are rarely updated or checked by security teams. D) Applications run without CSP protections, allowing model-inserted scripts to leak data to external hosts. | C10: D | D10: {=_xlfn.SWITCH(C10,"A", 0.25,"B", 0.5, "C", 0.75,"D", 1)} -> 1
A11: Insecure Output Handling | B11: Output Hallucination Content Filtering A) Fact-checking engines compare model responses against verified databases, dropping unaligned outputs instantly. B) Filters look for specific banned phrases or keywords, but lack semantic checking to identify logical errors. C) Evaluation relies on out-of-the-box model parameters (e.g., lowering temperature) without external validation checks. D) Outputs flow directly to end users without validation, exposing operations to hallucinated content risks. | C11: D | D11: {=_xlfn.SWITCH(C11,"A", 0.25,"B", 0.5, "C", 0.75,"D", 1)} -> 1
A12: Training Data Privacy & PII Leakage | B12: Fine-Tuning PII Redaction A) Automated pipelines sanitize fine-tuning data, using cryptographic tokens to replace sensitive PII fields. B) Data preparation strips clear text fields manually, but lacks validation to catch nested or indirect PII vectors. C) Datasets rely on general corporate filtering policies without specific tuning for LLM memorization risks. D) Fine-tuning processes ingest raw corporate data directly, allowing the model to memorize sensitive information. | C12: D | D12: {=_xlfn.SWITCH(C12,"A", 0.25,"B", 0.5, "C", 0.75,"D", 1)} -> 1
A13: Training Data Privacy & PII Leakage | B13: Retrieval-Augmented Generation (RAG) Scoping A) RAG search queries check user authorization parameters dynamically before retrieving vector database entries. B) Vector storage limits access by department, but lacks granular file-level validation checks. C) Vector searches match query text directly, allowing access to any indexed data within the shared workspace. D) The RAG engine accesses all internal data stores globally, exposing sensitive records across user profiles. | C13: D | D13: {=_xlfn.SWITCH(C13,"A", 0.25,"B", 0.5, "C", 0.75,"D", 1)} -> 1
... A75: DevSecOps for GenAI & Pipeline Auditing | B75: Software Bill of Materials (SBOM) for Model Components A) Build pipelines generate verified SBOM maps automatically and drop any build containing known vulnerable model libraries. B) Dependency scanners track package updates, but lack automated systems to block vulnerable components. C) Library updates are evaluated manually during scheduled application optimization sweeps. D) Workloads run unvetted open-source libraries without visibility into nested component dependencies. | C75: D | D75: {=_xlfn.SWITCH(C75,"A", 0.25,"B", 0.5, "C", 0.75,"D", 1)} -> 1
A77: © 2026 Amit Kulkarni All rights reserved

Sheet Dashboards
A1: Category | B1: Category Score Formula | C1: Weight Multipliers | D1: Weighted Scores
A2: Prompt Injection Defenses | B2: =AVERAGEIF(Inputs!$A$2:$A$73, A2, Inputs!$D$2:$D$72) -> 1 | C2: 3 | D2: =B2*C2 -> 3
A3: Insecure Output Handling | B3: =AVERAGEIF(Inputs!$A$2:$A$73, A3, Inputs!$D$2:$D$72) -> 1 | C3: 3 | D3: =B3*C3 -> 3
A4: Training Data Privacy & PII Leakage | B4: =AVERAGEIF(Inputs!$A$2:$A$73, A4, Inputs!$D$2:$D$72) -> 1 | C4: 2 | D4: =B4*C4 -> 2
A5: Excessive Agency & Authorization Guardrails | B5: =AVERAGEIF(Inputs!$A$2:$A$73, A5, Inputs!$D$2:$D$72) -> 1 | C5: 2 | D5: =B5*C5 -> 2
A6: Model Data Poisoning & Supply Chain | B6: =AVERAGEIF(Inputs!$A$2:$A$73, A6, Inputs!$D$2:$D$72) -> 1 | C6: 3 | D6: =B6*C6 -> 3
A7: Model Inversion & Membership Inference | B7: =AVERAGEIF(Inputs!$A$2:$A$73, A7, Inputs!$D$2:$D$72) -> 0.95 | C7: 2 | D7: =B7*C7 -> 1.9
A8: Overreliance, Hallucination & Output Validation | B8: =AVERAGEIF(Inputs!$A$2:$A$73, A8, Inputs!$D$2:$D$72) -> 1 | C8: 1 | D8: =B8*C8 -> 1
A9: Insecure Plugin & Agency Design | B9: =AVERAGEIF(Inputs!$A$2:$A$73, A9, Inputs!$D$2:$D$72) -> 1 | C9: 3 | D9: =B9*C9 -> 3
A10: Serverless/Vector Database Network Isolation | B10: =AVERAGEIF(Inputs!$A$2:$A$73, A10, Inputs!$D$2:$D$72) -> 1 | C10: 2 | D10: =B10*C10 -> 2
A11: AI Logging, Shadow LLM Detection & Observability | B11: =AVERAGEIF(Inputs!$A$2:$A$73, A11, Inputs!$D$2:$D$72) -> 1 | C11: 2 | D11: =B11*C11 -> 2
A12: AI Infrastructure Configuration Drift & IaC | B12: =AVERAGEIF(Inputs!$A$2:$A$73, A12, Inputs!$D$2:$D$72) -> 1 | C12: 1 | D12: =B12*C12 -> 1
A13: Cross-Model/SaaS AI API Trust Boundaries | B13: =AVERAGEIF(Inputs!$A$2:$A$75, A13, Inputs!$D$2:$D$75) -> 0.7 | C13: 2 | D13: =B13*C13 -> 1.4
A14: Training Data & Model Secret Theft | B14: =AVERAGEIF(Inputs!$A$2:$A$75, A14, Inputs!$D$2:$D$75) -> 1 | C14: 3 | D14: =B14*C14 -> 3
A15: Model Red Teaming & Continuous Evaluation | B15: =AVERAGEIF(Inputs!$A$2:$A$75, A15, Inputs!$D$2:$D$75) -> 1 | C15: 1 | D15: =B15*C15 -> 1
A16: DevSecOps for GenAI & Pipeline Auditing | B16: =AVERAGEIF(Inputs!$A$2:$A$75, A16, Inputs!$D$2:$D$75) -> 1 | C16: 2 | D16: =B16*C16 -> 2
B20: Global Weighted Score | C20: =SUM(D2:D16)/SUM(C2:C16) -> 0.978125
B22: Security Posturing Forecast State | C22: =IF(C20<=40%, "🟢 Optimized AI Security State", IF(C20<=60%, "🟡 Resilient AI Security State", IF(C20<=80%, "🟠 Elevated AI Risk Exposure", "🔴 Critical AI Security Threat Posture"))) -> 🔴 Critical AI Security Threat Posture
B26: Row Labels | C26: Sum of Weight Multipliers | D26: Sum of Weighted Scores
B27: AI Infrastructure Configuration Drift & IaC | C27: 2 | D27: 1.4
B28: AI Logging, Shadow LLM Detection & Observability | C28: 3 | D28: 2.1
B29: Cross-Model/SaaS AI API Trust Boundaries | C29: 2 | D29: 1.1
B30: DevSecOps for GenAI & Pipeline Auditing | C30: 2 | D30: 0.5
B31: Excessive Agency & Authorization Guardrails | C31: 2 | D31: 1.6
B32: Insecure Output Handling | C32: 3 | D32: 1.65
B33: Insecure Plugin & Agency Design | C33: 1 | D33: 0.8
B34: Model Data Poisoning & Supply Chain | C34: 2 | D34: 0.875
B35: Model Inversion & Membership Inference | C35: 1 | D35: 0.65
B36: Model Red Teaming & Continuous Evaluation | C36: 3 | D36: 2.4
B37: Overreliance, Hallucination & Output Validation | C37: 1 | D37: 0.65
B38: Prompt Injection Defenses | C38: 3 | D38: 2.1
... B42: Grand Total | C42: 30 | D42: 19.025
A44: © 2026 Amit Kulkarni All rights reserved

Sheet Results Interpretation
A1: States | B1: Definitions | C1: Operational Impact
A2: 🛡️ State 1: Optimized AI Security State(Score: 0% – 40%) | B2: The organization has a low risk exposure with mature, proactive AI security controls, continuous monitoring, and strict governance frameworks. | C2: Operations run with minimal disruption, compliance penalties are avoided, and customer trust remains exceptionally high.
A3: ⚠️ State 2: Resilient AI Security State (Score: 41% – 60%) | B3: Core security controls are active, allowing the organization to defend against common AI vulnerabilities and recover quickly from minor incidents. | C3: Business continuity is maintained, though occasional security patches, minor remediation efforts, and standard policy updates are required.
A4: 🚨 State 3: Elevated AI Risk Exposure (Score: 61% – 80%) | B4: Significant gaps exist in AI data governance, model monitoring, or access controls, leaving the organization highly vulnerable to exploitation. | C4: Increased likelihood of data leaks, compliance violations, intellectual property theft, and financial losses due to successful adversarial attacks.
A5: ☠️ State 4: Critical AI Security Threat Posture (Score: 81% – 100%) | B5: The AI environment lacks fundamental security guardrails, suffering from active exploits, massive vulnerabilities, or total lack of oversight. | C5: Severe operational downtime, catastrophic data breaches, legal liabilities, regulatory shutdown of AI services, and permanent brand damage.
A7: © 2026 Amit Kulkarni All rights reserved
